{
  "creator": "Yosys 0.60 (git sha1 5bafeb77dc71e054fa331ab9efa613e6fb0a1c49, clang++ 17.0.0 -fPIC -O3)",
  "modules": {
    "top": {
      "attributes": {
        "top": "00000000000000000000000000000001",
        "src": "designs/779/top.sv:1.1-42.10"
      },
      "ports": {
        "input_data": {
          "direction": "input",
          "bits": [ 2, 3, 4, 5, 6, 7, 8 ]
        },
        "output_data": {
          "direction": "output",
          "bits": [ 9, 10, 11, 12, 13, 14, 15, 16, 17 ]
        }
      },
      "cells": {
        "$add$designs/779/top.sv:22$4": {
          "hide_name": 1,
          "type": "$add",
          "parameters": {
            "A_SIGNED": "00000000000000000000000000000000",
            "A_WIDTH": "00000000000000000000000000010110",
            "B_SIGNED": "00000000000000000000000000000000",
            "B_WIDTH": "00000000000000000000000000010111",
            "Y_WIDTH": "00000000000000000000000000010111"
          },
          "attributes": {
            "src": "designs/779/top.sv:22.30-22.72"
          },
          "port_directions": {
            "A": "input",
            "B": "input",
            "Y": "output"
          },
          "connections": {
            "A": [ 2, "1", 4, 5, 6, 7, "1", "0", "0", "1", "1", "0", "0", "0", "0", "1", "1", "1", "0", "0", "0", "1" ],
            "B": [ 18, 19, 20, 21, 22, 23, 24, "1", "1", "1", "1", "1", "1", "1", "1", "1", "1", "1", "1", "1", "1", "1", "1" ],
            "Y": [ 25, 26, 27, 28, 29, 30, 31, 32, 33, 34, 35, 36, 37, 38, 39, 40, 41, 42, 43, 44, 45, 46, 47 ]
          }
        },
        "$add$designs/779/top.sv:23$6": {
          "hide_name": 1,
          "type": "$add",
          "parameters": {
            "A_SIGNED": "00000000000000000000000000000000",
            "A_WIDTH": "00000000000000000000000000010111",
            "B_SIGNED": "00000000000000000000000000000000",
            "B_WIDTH": "00000000000000000000000000001101",
            "Y_WIDTH": "00000000000000000000000000010111"
          },
          "attributes": {
            "src": "designs/779/top.sv:23.23-23.64"
          },
          "port_directions": {
            "A": "input",
            "B": "input",
            "Y": "output"
          },
          "connections": {
            "A": [ 48, 49, 50, 51, 52, 53, 54, 55, 56, 57, 58, 59, 60, 61, 62, 63, 64, 65, 66, 67, 68, 69, 70 ],
            "B": [ 25, 26, 27, 28, 29, 30, 31, 32, 33, 34, 35, 36, 37 ],
            "Y": [ 71, 72, 73, 74, 75, 76, 77, 78, 79, 80, 81, 82, 83, 84, 85, 86, 87, 88, 89, 90, 91, 92, 93 ]
          }
        },
        "$add$designs/779/top.sv:24$14": {
          "hide_name": 1,
          "type": "$add",
          "parameters": {
            "A_SIGNED": "00000000000000000000000000000000",
            "A_WIDTH": "00000000000000000000000000011110",
            "B_SIGNED": "00000000000000000000000000000000",
            "B_WIDTH": "00000000000000000000000000000010",
            "Y_WIDTH": "00000000000000000000000000011110"
          },
          "attributes": {
            "src": "designs/779/top.sv:24.23-24.103"
          },
          "port_directions": {
            "A": "input",
            "B": "input",
            "Y": "output"
          },
          "connections": {
            "A": [ 94, 95, 96, 97, 98, 99, 100, 101, 102, 103, 104, 105, 106, 107, 108, 109, 110, 111, 112, 113, 114, 115, 116, 117, 118, 119, 120, 121, 122, 123 ],
            "B": [ 124, 125 ],
            "Y": [ 126, 127, 128, 129, 130, 131, 132, 133, 134, 135, 136, 137, 138, 139, 140, 141, 142, 143, 144, 145, 146, 147, 148, 149, 150, 151, 152, 153, 154, 155 ]
          }
        },
        "$add$designs/779/top.sv:24$8": {
          "hide_name": 1,
          "type": "$add",
          "parameters": {
            "A_SIGNED": "00000000000000000000000000000000",
            "A_WIDTH": "00000000000000000000000000010111",
            "B_SIGNED": "00000000000000000000000000000000",
            "B_WIDTH": "00000000000000000000000000000010",
            "Y_WIDTH": "00000000000000000000000000011000"
          },
          "attributes": {
            "src": "designs/779/top.sv:24.27-24.42"
          },
          "port_directions": {
            "A": "input",
            "B": "input",
            "Y": "output"
          },
          "connections": {
            "A": [ 25, 26, 27, 28, 29, 30, 31, 32, 33, 34, 35, 36, 37, 38, 39, 40, 41, 42, 43, 44, 45, 46, 47 ],
            "B": [ 124, 125 ],
            "Y": [ 156, 157, 158, 159, 160, 161, 162, 163, 164, 165, 166, 167, 168, 169, 170, 171, 172, 173, 174, 175, 176, 177, 178, 179 ]
          }
        },
        "$add$designs/779/top.sv:24$9": {
          "hide_name": 1,
          "type": "$add",
          "parameters": {
            "A_SIGNED": "00000000000000000000000000000000",
            "A_WIDTH": "00000000000000000000000000011000",
            "B_SIGNED": "00000000000000000000000000000000",
            "B_WIDTH": "00000000000000000000000000000001",
            "Y_WIDTH": "00000000000000000000000000011001"
          },
          "attributes": {
            "src": "designs/779/top.sv:24.26-24.57"
          },
          "port_directions": {
            "A": "input",
            "B": "input",
            "Y": "output"
          },
          "connections": {
            "A": [ 156, 157, 158, 159, 160, 161, 162, 163, 164, 165, 166, 167, 168, 169, 170, 171, 172, 173, 174, 175, 176, 177, 178, 179 ],
            "B": [ 125 ],
            "Y": [ 180, 181, 182, 183, 184, 185, 186, 187, 188, 189, 190, 191, 192, 193, 194, 195, 196, 197, 198, 199, 200, 201, 202, 203, 204 ]
          }
        },
        "$add$designs/779/top.sv:26$30": {
          "hide_name": 1,
          "type": "$add",
          "parameters": {
            "A_SIGNED": "00000000000000000000000000000000",
            "A_WIDTH": "00000000000000000000000000000100",
            "B_SIGNED": "00000000000000000000000000000000",
            "B_WIDTH": "00000000000000000000000000000100",
            "Y_WIDTH": "00000000000000000000000000000100"
          },
          "attributes": {
            "src": "designs/779/top.sv:26.22-26.102"
          },
          "port_directions": {
            "A": "input",
            "B": "input",
            "Y": "output"
          },
          "connections": {
            "A": [ 205, 206, 207, 208 ],
            "B": [ 209, "1", "1", "1" ],
            "Y": [ 210, 211, 212, 213 ]
          }
        },
        "$add$designs/779/top.sv:29$41": {
          "hide_name": 1,
          "type": "$add",
          "parameters": {
            "A_SIGNED": "00000000000000000000000000000000",
            "A_WIDTH": "00000000000000000000000000011110",
            "B_SIGNED": "00000000000000000000000000000000",
            "B_WIDTH": "00000000000000000000000000011110",
            "Y_WIDTH": "00000000000000000000000000011110"
          },
          "attributes": {
            "src": "designs/779/top.sv:29.26-29.70"
          },
          "port_directions": {
            "A": "input",
            "B": "input",
            "Y": "output"
          },
          "connections": {
            "A": [ 214, 215, 216, 217, 218, 219, 220, 221, 222, 223, 224, 225, 226, 227, 228, 229, 230, 231, 232, 233, 234, 235, 236, 237, 238, 239, 240, 241, 242, 243 ],
            "B": [ 244, 245, 246, 247, 248, 249, 250, 251, 252, 253, 254, 255, 256, 257, 258, 259, 260, 261, 262, 263, 264, 265, 266, "0", "0", "0", "0", "0", "0", "0" ],
            "Y": [ 267, 268, 269, 270, 271, 272, 273, 274, 275, 276, 277, 278, 279, 280, 281, 282, 283, 284, 285, 286, 287, 288, 289, 290, 291, 292, 293, 294, 295, 296 ]
          }
        },
        "$add$designs/779/top.sv:29$45": {
          "hide_name": 1,
          "type": "$add",
          "parameters": {
            "A_SIGNED": "00000000000000000000000000000000",
            "A_WIDTH": "00000000000000000000000000011000",
            "B_SIGNED": "00000000000000000000000000000000",
            "B_WIDTH": "00000000000000000000000000000111",
            "Y_WIDTH": "00000000000000000000000000011000"
          },
          "attributes": {
            "src": "designs/779/top.sv:29.22-29.119"
          },
          "port_directions": {
            "A": "input",
            "B": "input",
            "Y": "output"
          },
          "connections": {
            "A": [ 297, 298, 299, 300, 301, 302, 303, 304, 305, 306, 307, 308, 309, 310, 311, 312, 313, 314, 315, 316, 317, 318, 319, 320 ],
            "B": [ 2, 3, 4, 5, 6, 7, 8 ],
            "Y": [ 321, 322, 323, 324, 325, 326, 327, 328, 329, 330, 331, 332, 333, 334, 335, 336, 337, 338, 339, 340, 341, 342, 343, 344 ]
          }
        },
        "$add$designs/779/top.sv:30$46": {
          "hide_name": 1,
          "type": "$add",
          "parameters": {
            "A_SIGNED": "00000000000000000000000000000000",
            "A_WIDTH": "00000000000000000000000000000001",
            "B_SIGNED": "00000000000000000000000000000000",
            "B_WIDTH": "00000000000000000000000000010111",
            "Y_WIDTH": "00000000000000000000000000011000"
          },
          "attributes": {
            "src": "designs/779/top.sv:30.28-30.43"
          },
          "port_directions": {
            "A": "input",
            "B": "input",
            "Y": "output"
          },
          "connections": {
            "A": [ 345 ],
            "B": [ 25, 26, 27, 28, 29, 30, 31, 32, 33, 34, 35, 36, 37, 38, 39, 40, 41, 42, 43, 44, 45, 46, 47 ],
            "Y": [ 346, 347, 348, 349, 350, 351, 352, 353, 354, 355, 356, 357, 358, 359, 360, 361, 362, 363, 364, 365, 366, 367, 368, 369 ]
          }
        },
        "$add$designs/779/top.sv:30$51": {
          "hide_name": 1,
          "type": "$add",
          "parameters": {
            "A_SIGNED": "00000000000000000000000000000000",
            "A_WIDTH": "00000000000000000000000000011111",
            "B_SIGNED": "00000000000000000000000000000000",
            "B_WIDTH": "00000000000000000000000000010111",
            "Y_WIDTH": "00000000000000000000000000011111"
          },
          "attributes": {
            "src": "designs/779/top.sv:30.25-30.81"
          },
          "port_directions": {
            "A": "input",
            "B": "input",
            "Y": "output"
          },
          "connections": {
            "A": [ 370, 371, 372, 373, 374, 375, 376, 377, 378, 379, 380, 381, 382, 383, 384, 385, 386, 387, 388, 389, 390, 391, 392, 393, 394, 395, 396, 397, 398, 399, 400 ],
            "B": [ 25, 26, 27, 28, 29, 30, 31, 32, 33, 34, 35, 36, 37, 38, 39, 40, 41, 42, 43, 44, 45, 46, 47 ],
            "Y": [ 401, 402, 403, 404, 405, 406, 407, 408, 409, 410, 411, 412, 413, 414, 415, 416, 417, 418, 419, 420, 421, 422, 423, 424, 425, 426, 427, 428, 429, 430, 431 ]
          }
        },
        "$add$designs/779/top.sv:33$61": {
          "hide_name": 1,
          "type": "$add",
          "parameters": {
            "A_SIGNED": "00000000000000000000000000000000",
            "A_WIDTH": "00000000000000000000000000011111",
            "B_SIGNED": "00000000000000000000000000000000",
            "B_WIDTH": "00000000000000000000000000000100",
            "Y_WIDTH": "00000000000000000000000000011111"
          },
          "attributes": {
            "src": "designs/779/top.sv:33.39-33.71"
          },
          "port_directions": {
            "A": "input",
            "B": "input",
            "Y": "output"
          },
          "connections": {
            "A": [ 432, 433, 434, 435, 436, 437, 438, 439, 440, 441, 442, 443, 444, 445, 446, 447, 448, 449, 450, 451, 452, 453, 454, 455, 456, 457, 458, 459, 460, 461, 462 ],
            "B": [ 210, 211, 212, 213 ],
            "Y": [ 463, 464, 465, 466, 467, 468, 469, 470, 471, 472, 473, 474, 475, 476, 477, 478, 479, 480, 481, 482, 483, 484, 485, 486, 487, 488, 489, 490, 491, 492, 493 ]
          }
        },
        "$add$designs/779/top.sv:34$74": {
          "hide_name": 1,
          "type": "$add",
          "parameters": {
            "A_SIGNED": "00000000000000000000000000000000",
            "A_WIDTH": "00000000000000000000000000011001",
            "B_SIGNED": "00000000000000000000000000000000",
            "B_WIDTH": "00000000000000000000000000001010",
            "Y_WIDTH": "00000000000000000000000000011001"
          },
          "attributes": {
            "src": "designs/779/top.sv:34.25-34.83"
          },
          "port_directions": {
            "A": "input",
            "B": "input",
            "Y": "output"
          },
          "connections": {
            "A": [ 494, 495, 496, 497, 498, 499, 500, 501, 502, 503, 504, 505, 506, 507, 508, 509, 510, 511, 512, 513, 514, 515, 516, 517, 518 ],
            "B": [ 245, 246, 247, 248, 249, 250, 251, 252, 253, 254 ],
            "Y": [ 519, 520, 521, 522, 523, 524, 525, 526, 527, 528, 529, 530, 531, 532, 533, 534, 535, 536, 537, 538, 539, 540, 541, 542, 543 ]
          }
        },
        "$add$designs/779/top.sv:36$82": {
          "hide_name": 1,
          "type": "$add",
          "parameters": {
            "A_SIGNED": "00000000000000000000000000000000",
            "A_WIDTH": "00000000000000000000000000000001",
            "B_SIGNED": "00000000000000000000000000000000",
            "B_WIDTH": "00000000000000000000000000010000",
            "Y_WIDTH": "00000000000000000000000000010000"
          },
          "attributes": {
            "src": "designs/779/top.sv:36.72-36.90"
          },
          "port_directions": {
            "A": "input",
            "B": "input",
            "Y": "output"
          },
          "connections": {
            "A": [ 345 ],
            "B": [ 544, 545, 546, 547, 548, 549, 550, 551, 552, 553, 554, 555, 556, 557, 558, 559 ],
            "Y": [ 560, 561, 562, 563, 564, 565, 566, 567, 568, 569, 570, 571, 572, 573, 574, 575 ]
          }
        },
        "$and$designs/779/top.sv:26$26": {
          "hide_name": 1,
          "type": "$and",
          "parameters": {
            "A_SIGNED": "00000000000000000000000000000000",
            "A_WIDTH": "00000000000000000000000000000100",
            "B_SIGNED": "00000000000000000000000000000000",
            "B_WIDTH": "00000000000000000000000000000100",
            "Y_WIDTH": "00000000000000000000000000000100"
          },
          "attributes": {
            "src": "designs/779/top.sv:26.24-26.79"
          },
          "port_directions": {
            "A": "input",
            "B": "input",
            "Y": "output"
          },
          "connections": {
            "A": [ 576, 577, 578, 579 ],
            "B": [ 25, 26, 27, 28 ],
            "Y": [ 580, 206, 207, 208 ]
          }
        },
        "$and$designs/779/top.sv:34$78": {
          "hide_name": 1,
          "type": "$and",
          "parameters": {
            "A_SIGNED": "00000000000000000000000000000000",
            "A_WIDTH": "00000000000000000000000000001001",
            "B_SIGNED": "00000000000000000000000000000000",
            "B_WIDTH": "00000000000000000000000000001001",
            "Y_WIDTH": "00000000000000000000000000001001"
          },
          "attributes": {
            "src": "designs/779/top.sv:34.23-34.112"
          },
          "port_directions": {
            "A": "input",
            "B": "input",
            "Y": "output"
          },
          "connections": {
            "A": [ 581, 582, 583, 584, 585, 586, 587, 588, 589 ],
            "B": [ 590, 591, 592, 593, 594, 595, 596, 597, 598 ],
            "Y": [ 599, 600, 601, 602, 603, 604, 605, 606, 607 ]
          }
        },
        "$and$designs/779/top.sv:40$95": {
          "hide_name": 1,
          "type": "$and",
          "parameters": {
            "A_SIGNED": "00000000000000000000000000000000",
            "A_WIDTH": "00000000000000000000000000001001",
            "B_SIGNED": "00000000000000000000000000000000",
            "B_WIDTH": "00000000000000000000000000001001",
            "Y_WIDTH": "00000000000000000000000000001001"
          },
          "attributes": {
            "src": "designs/779/top.sv:40.27-40.44"
          },
          "port_directions": {
            "A": "input",
            "B": "input",
            "Y": "output"
          },
          "connections": {
            "A": [ 599, 600, 601, 602, 603, 604, 605, 606, 607 ],
            "B": [ 608, 609, 610, 611, 612, 613, 614, 615, 616 ],
            "Y": [ 9, 10, 11, 12, 13, 14, 15, 16, 17 ]
          }
        },
        "$auto$opt_expr.cc:276:group_cell_inputs$109": {
          "hide_name": 1,
          "type": "$not",
          "parameters": {
            "A_SIGNED": "00000000000000000000000000000000",
            "A_WIDTH": "00000000000000000000000000000111",
            "Y_WIDTH": "00000000000000000000000000000111"
          },
          "attributes": {
          },
          "port_directions": {
            "A": "input",
            "Y": "output"
          },
          "connections": {
            "A": [ 2, 3, 4, 5, 6, 7, 8 ],
            "Y": [ 18, 19, 20, 21, 22, 23, 24 ]
          }
        },
        "$auto$opt_expr.cc:276:group_cell_inputs$113": {
          "hide_name": 1,
          "type": "$and",
          "parameters": {
            "A_SIGNED": "00000000000000000000000000000000",
            "A_WIDTH": "00000000000000000000000000010111",
            "B_SIGNED": "00000000000000000000000000000000",
            "B_WIDTH": "00000000000000000000000000010111",
            "Y_WIDTH": "00000000000000000000000000010111"
          },
          "attributes": {
          },
          "port_directions": {
            "A": "input",
            "B": "input",
            "Y": "output"
          },
          "connections": {
            "A": [ 126, 127, 128, 129, 130, 131, 132, 133, 134, 135, 136, 137, 138, 139, 140, 141, 142, 143, 144, 145, 146, 147, 148 ],
            "B": [ 25, 26, 27, 28, 29, 30, 31, 32, 33, 34, 35, 36, 37, 38, 39, 40, 41, 42, 43, 44, 45, 46, 47 ],
            "Y": [ 244, 245, 246, 247, 248, 249, 250, 251, 252, 253, 254, 255, 256, 257, 258, 259, 260, 261, 262, 263, 264, 265, 266 ]
          }
        },
        "$auto$opt_expr.cc:276:group_cell_inputs$117": {
          "hide_name": 1,
          "type": "$xor",
          "parameters": {
            "A_SIGNED": "00000000000000000000000000000000",
            "A_WIDTH": "00000000000000000000000000000001",
            "B_SIGNED": "00000000000000000000000000000000",
            "B_WIDTH": "00000000000000000000000000000001",
            "Y_WIDTH": "00000000000000000000000000000001"
          },
          "attributes": {
          },
          "port_directions": {
            "A": "input",
            "B": "input",
            "Y": "output"
          },
          "connections": {
            "A": [ 617 ],
            "B": [ 124 ],
            "Y": [ 618 ]
          }
        },
        "$auto$opt_expr.cc:276:group_cell_inputs$120": {
          "hide_name": 1,
          "type": "$xor",
          "parameters": {
            "A_SIGNED": "00000000000000000000000000000000",
            "A_WIDTH": "00000000000000000000000000000100",
            "B_SIGNED": "00000000000000000000000000000000",
            "B_WIDTH": "00000000000000000000000000000100",
            "Y_WIDTH": "00000000000000000000000000000100"
          },
          "attributes": {
          },
          "port_directions": {
            "A": "input",
            "B": "input",
            "Y": "output"
          },
          "connections": {
            "A": [ 244, 245, 246, 247 ],
            "B": [ 3, 4, 5, 6 ],
            "Y": [ 619, 620, 621, 622 ]
          }
        },
        "$auto$opt_expr.cc:276:group_cell_inputs$123": {
          "hide_name": 1,
          "type": "$or",
          "parameters": {
            "A_SIGNED": "00000000000000000000000000000000",
            "A_WIDTH": "00000000000000000000000000000001",
            "B_SIGNED": "00000000000000000000000000000000",
            "B_WIDTH": "00000000000000000000000000000001",
            "Y_WIDTH": "00000000000000000000000000000001"
          },
          "attributes": {
          },
          "port_directions": {
            "A": "input",
            "B": "input",
            "Y": "output"
          },
          "connections": {
            "A": [ 580 ],
            "B": [ 345 ],
            "Y": [ 205 ]
          }
        },
        "$auto$opt_expr.cc:276:group_cell_inputs$130": {
          "hide_name": 1,
          "type": "$not",
          "parameters": {
            "A_SIGNED": "00000000000000000000000000000000",
            "A_WIDTH": "00000000000000000000000000010111",
            "Y_WIDTH": "00000000000000000000000000010111"
          },
          "attributes": {
          },
          "port_directions": {
            "A": "input",
            "Y": "output"
          },
          "connections": {
            "A": [ 25, 26, 27, 28, 29, 30, 31, 32, 33, 34, 35, 36, 37, 38, 39, 40, 41, 42, 43, 44, 45, 46, 47 ],
            "Y": [ 623, 624, 625, 626, 627, 628, 629, 630, 631, 632, 633, 634, 635, 636, 637, 638, 639, 640, 641, 642, 643, 644, 645 ]
          }
        },
        "$auto$opt_expr.cc:276:group_cell_inputs$134": {
          "hide_name": 1,
          "type": "$and",
          "parameters": {
            "A_SIGNED": "00000000000000000000000000000000",
            "A_WIDTH": "00000000000000000000000000001000",
            "B_SIGNED": "00000000000000000000000000000000",
            "B_WIDTH": "00000000000000000000000000001000",
            "Y_WIDTH": "00000000000000000000000000001000"
          },
          "attributes": {
          },
          "port_directions": {
            "A": "input",
            "B": "input",
            "Y": "output"
          },
          "connections": {
            "A": [ 267, 268, 269, 270, 271, 272, 273, 274 ],
            "B": [ 646, 647, 648, 649, 650, 651, 652, 653 ],
            "Y": [ 654, 655, 656, 657, 658, 659, 660, 661 ]
          }
        },
        "$auto$opt_expr.cc:276:group_cell_inputs$138": {
          "hide_name": 1,
          "type": "$not",
          "parameters": {
            "A_SIGNED": "00000000000000000000000000000000",
            "A_WIDTH": "00000000000000000000000000001001",
            "Y_WIDTH": "00000000000000000000000000001001"
          },
          "attributes": {
          },
          "port_directions": {
            "A": "input",
            "Y": "output"
          },
          "connections": {
            "A": [ 25, 26, 27, 28, 29, 30, 31, 32, 33 ],
            "Y": [ 662, 663, 664, 665, 666, 667, 668, 669, 670 ]
          }
        },
        "$auto$opt_expr.cc:276:group_cell_inputs$142": {
          "hide_name": 1,
          "type": "$and",
          "parameters": {
            "A_SIGNED": "00000000000000000000000000000000",
            "A_WIDTH": "00000000000000000000000000000010",
            "B_SIGNED": "00000000000000000000000000000000",
            "B_WIDTH": "00000000000000000000000000000010",
            "Y_WIDTH": "00000000000000000000000000000010"
          },
          "attributes": {
          },
          "port_directions": {
            "A": "input",
            "B": "input",
            "Y": "output"
          },
          "connections": {
            "A": [ 401, 402 ],
            "B": [ 124, 125 ],
            "Y": [ 671, 672 ]
          }
        },
        "$auto$opt_expr.cc:276:group_cell_inputs$146": {
          "hide_name": 1,
          "type": "$and",
          "parameters": {
            "A_SIGNED": "00000000000000000000000000000000",
            "A_WIDTH": "00000000000000000000000000000001",
            "B_SIGNED": "00000000000000000000000000000000",
            "B_WIDTH": "00000000000000000000000000000001",
            "Y_WIDTH": "00000000000000000000000000000001"
          },
          "attributes": {
          },
          "port_directions": {
            "A": "input",
            "B": "input",
            "Y": "output"
          },
          "connections": {
            "A": [ 673 ],
            "B": [ 125 ],
            "Y": [ 674 ]
          }
        },
        "$auto$opt_expr.cc:276:group_cell_inputs$150": {
          "hide_name": 1,
          "type": "$and",
          "parameters": {
            "A_SIGNED": "00000000000000000000000000000000",
            "A_WIDTH": "00000000000000000000000000000001",
            "B_SIGNED": "00000000000000000000000000000000",
            "B_WIDTH": "00000000000000000000000000000001",
            "Y_WIDTH": "00000000000000000000000000000001"
          },
          "attributes": {
          },
          "port_directions": {
            "A": "input",
            "B": "input",
            "Y": "output"
          },
          "connections": {
            "A": [ 341 ],
            "B": [ 345 ],
            "Y": [ 675 ]
          }
        },
        "$auto$opt_expr.cc:276:group_cell_inputs$158": {
          "hide_name": 1,
          "type": "$not",
          "parameters": {
            "A_SIGNED": "00000000000000000000000000000000",
            "A_WIDTH": "00000000000000000000000000000001",
            "Y_WIDTH": "00000000000000000000000000000001"
          },
          "attributes": {
          },
          "port_directions": {
            "A": "input",
            "Y": "output"
          },
          "connections": {
            "A": [ 345 ],
            "Y": [ 209 ]
          }
        },
        "$auto$opt_expr.cc:276:group_cell_inputs$165": {
          "hide_name": 1,
          "type": "$not",
          "parameters": {
            "A_SIGNED": "00000000000000000000000000000000",
            "A_WIDTH": "00000000000000000000000000001000",
            "Y_WIDTH": "00000000000000000000000000001000"
          },
          "attributes": {
          },
          "port_directions": {
            "A": "input",
            "Y": "output"
          },
          "connections": {
            "A": [ 646, 647, 648, 649, 650, 651, 652, 653 ],
            "Y": [ 676, 677, 678, 679, 680, 681, 682, 683 ]
          }
        },
        "$auto$opt_expr.cc:276:group_cell_inputs$169": {
          "hide_name": 1,
          "type": "$xor",
          "parameters": {
            "A_SIGNED": "00000000000000000000000000000000",
            "A_WIDTH": "00000000000000000000000000000010",
            "B_SIGNED": "00000000000000000000000000000000",
            "B_WIDTH": "00000000000000000000000000000010",
            "Y_WIDTH": "00000000000000000000000000000010"
          },
          "attributes": {
          },
          "port_directions": {
            "A": "input",
            "B": "input",
            "Y": "output"
          },
          "connections": {
            "A": [ 684, 685 ],
            "B": [ 124, 125 ],
            "Y": [ 686, 687 ]
          }
        },
        "$auto$opt_expr.cc:276:group_cell_inputs$172": {
          "hide_name": 1,
          "type": "$not",
          "parameters": {
            "A_SIGNED": "00000000000000000000000000000000",
            "A_WIDTH": "00000000000000000000000000000001",
            "Y_WIDTH": "00000000000000000000000000000001"
          },
          "attributes": {
          },
          "port_directions": {
            "A": "input",
            "Y": "output"
          },
          "connections": {
            "A": [ 125 ],
            "Y": [ 688 ]
          }
        },
        "$auto$opt_expr.cc:276:group_cell_inputs$176": {
          "hide_name": 1,
          "type": "$not",
          "parameters": {
            "A_SIGNED": "00000000000000000000000000000000",
            "A_WIDTH": "00000000000000000000000000001011",
            "Y_WIDTH": "00000000000000000000000000001011"
          },
          "attributes": {
          },
          "port_directions": {
            "A": "input",
            "Y": "output"
          },
          "connections": {
            "A": [ 244, 245, 246, 247, 248, 249, 250, 251, 252, 253, 254 ],
            "Y": [ 689, 690, 691, 692, 693, 694, 695, 696, 697, 698, 699 ]
          }
        },
        "$auto$opt_expr.cc:276:group_cell_inputs$180": {
          "hide_name": 1,
          "type": "$xor",
          "parameters": {
            "A_SIGNED": "00000000000000000000000000000000",
            "A_WIDTH": "00000000000000000000000000000001",
            "B_SIGNED": "00000000000000000000000000000000",
            "B_WIDTH": "00000000000000000000000000000001",
            "Y_WIDTH": "00000000000000000000000000000001"
          },
          "attributes": {
          },
          "port_directions": {
            "A": "input",
            "B": "input",
            "Y": "output"
          },
          "connections": {
            "A": [ 321 ],
            "B": [ 653 ],
            "Y": [ 700 ]
          }
        },
        "$auto$opt_expr.cc:276:group_cell_inputs$183": {
          "hide_name": 1,
          "type": "$or",
          "parameters": {
            "A_SIGNED": "00000000000000000000000000000000",
            "A_WIDTH": "00000000000000000000000000001000",
            "B_SIGNED": "00000000000000000000000000000000",
            "B_WIDTH": "00000000000000000000000000001000",
            "Y_WIDTH": "00000000000000000000000000001000"
          },
          "attributes": {
          },
          "port_directions": {
            "A": "input",
            "B": "input",
            "Y": "output"
          },
          "connections": {
            "A": [ 560, 561, 562, 563, 564, 565, 566, 567 ],
            "B": [ 646, 647, 648, 649, 650, 651, 652, 653 ],
            "Y": [ 701, 702, 703, 704, 705, 706, 707, 708 ]
          }
        },
        "$auto$opt_expr.cc:276:group_cell_inputs$192": {
          "hide_name": 1,
          "type": "$not",
          "parameters": {
            "A_SIGNED": "00000000000000000000000000000000",
            "A_WIDTH": "00000000000000000000000000010111",
            "Y_WIDTH": "00000000000000000000000000010111"
          },
          "attributes": {
          },
          "port_directions": {
            "A": "input",
            "Y": "output"
          },
          "connections": {
            "A": [ 244, 245, 246, 247, 248, 249, 250, 251, 252, 253, 254, 255, 256, 257, 258, 259, 260, 261, 262, 263, 264, 265, 266 ],
            "Y": [ 709, 710, 711, 712, 713, 714, 715, 716, 717, 718, 719, 720, 721, 722, 723, 724, 725, 726, 727, 728, 729, 730, 731 ]
          }
        },
        "$auto$opt_expr.cc:276:group_cell_inputs$196": {
          "hide_name": 1,
          "type": "$and",
          "parameters": {
            "A_SIGNED": "00000000000000000000000000000000",
            "A_WIDTH": "00000000000000000000000000001001",
            "B_SIGNED": "00000000000000000000000000000000",
            "B_WIDTH": "00000000000000000000000000001001",
            "Y_WIDTH": "00000000000000000000000000001001"
          },
          "attributes": {
          },
          "port_directions": {
            "A": "input",
            "B": "input",
            "Y": "output"
          },
          "connections": {
            "A": [ 732, 733, 734, 735, 736, 737, 738, 739, 740 ],
            "B": [ 662, 663, 664, 665, 666, 667, 668, 669, 670 ],
            "Y": [ 370, 371, 372, 373, 374, 375, 376, 377, 378 ]
          }
        },
        "$auto$opt_expr.cc:276:group_cell_inputs$203": {
          "hide_name": 1,
          "type": "$and",
          "parameters": {
            "A_SIGNED": "00000000000000000000000000000000",
            "A_WIDTH": "00000000000000000000000000000001",
            "B_SIGNED": "00000000000000000000000000000000",
            "B_WIDTH": "00000000000000000000000000000001",
            "Y_WIDTH": "00000000000000000000000000000001"
          },
          "attributes": {
          },
          "port_directions": {
            "A": "input",
            "B": "input",
            "Y": "output"
          },
          "connections": {
            "A": [ 675 ],
            "B": [ 244 ],
            "Y": [ 741 ]
          }
        },
        "$auto$opt_expr.cc:276:group_cell_inputs$207": {
          "hide_name": 1,
          "type": "$or",
          "parameters": {
            "A_SIGNED": "00000000000000000000000000000000",
            "A_WIDTH": "00000000000000000000000000000001",
            "B_SIGNED": "00000000000000000000000000000000",
            "B_WIDTH": "00000000000000000000000000000001",
            "Y_WIDTH": "00000000000000000000000000000001"
          },
          "attributes": {
          },
          "port_directions": {
            "A": "input",
            "B": "input",
            "Y": "output"
          },
          "connections": {
            "A": [ 741 ],
            "B": [ 209 ],
            "Y": [ 742 ]
          }
        },
        "$ge$designs/779/top.sv:25$16": {
          "hide_name": 1,
          "type": "$ge",
          "parameters": {
            "A_SIGNED": "00000000000000000000000000000000",
            "A_WIDTH": "00000000000000000000000000000010",
            "B_SIGNED": "00000000000000000000000000000000",
            "B_WIDTH": "00000000000000000000000000000111",
            "Y_WIDTH": "00000000000000000000000000000001"
          },
          "attributes": {
            "src": "designs/779/top.sv:25.27-25.47"
          },
          "port_directions": {
            "A": "input",
            "B": "input",
            "Y": "output"
          },
          "connections": {
            "A": [ 124, 125 ],
            "B": [ 2, 3, 4, 5, 6, 7, 8 ],
            "Y": [ 617 ]
          }
        },
        "$gt$designs/779/top.sv:25$20": {
          "hide_name": 1,
          "type": "$gt",
          "parameters": {
            "A_SIGNED": "00000000000000000000000000000000",
            "A_WIDTH": "00000000000000000000000000000001",
            "B_SIGNED": "00000000000000000000000000000000",
            "B_WIDTH": "00000000000000000000000000011110",
            "Y_WIDTH": "00000000000000000000000000000001"
          },
          "attributes": {
            "src": "designs/779/top.sv:25.24-25.85"
          },
          "port_directions": {
            "A": "input",
            "B": "input",
            "Y": "output"
          },
          "connections": {
            "A": [ 743 ],
            "B": [ 244, 245, 246, 247, 248, 249, 250, 251, 252, 253, 254, 255, 256, 257, 258, 259, 260, 261, 262, 263, 264, 265, 266, "0", "0", "0", "0", "0", "0", "0" ],
            "Y": [ 744 ]
          }
        },
        "$gt$designs/779/top.sv:25$23": {
          "hide_name": 1,
          "type": "$gt",
          "parameters": {
            "A_SIGNED": "00000000000000000000000000000000",
            "A_WIDTH": "00000000000000000000000000000001",
            "B_SIGNED": "00000000000000000000000000000000",
            "B_WIDTH": "00000000000000000000000000011110",
            "Y_WIDTH": "00000000000000000000000000000001"
          },
          "attributes": {
            "src": "designs/779/top.sv:25.22-25.109"
          },
          "port_directions": {
            "A": "input",
            "B": "input",
            "Y": "output"
          },
          "connections": {
            "A": [ 745 ],
            "B": [ 709, 710, 711, 712, 713, 714, 715, 716, 717, 718, 719, 720, 721, 722, 723, 724, 725, 726, 727, 728, 729, 730, 731, "1", "1", "1", "1", "1", "1", "1" ],
            "Y": [ 345 ]
          }
        },
        "$gt$designs/779/top.sv:34$70": {
          "hide_name": 1,
          "type": "$gt",
          "parameters": {
            "A_SIGNED": "00000000000000000000000000000000",
            "A_WIDTH": "00000000000000000000000000010000",
            "B_SIGNED": "00000000000000000000000000000000",
            "B_WIDTH": "00000000000000000000000000000010",
            "Y_WIDTH": "00000000000000000000000000000001"
          },
          "attributes": {
            "src": "designs/779/top.sv:34.27-34.49"
          },
          "port_directions": {
            "A": "input",
            "B": "input",
            "Y": "output"
          },
          "connections": {
            "A": [ 746, 747, 748, 749, 750, 751, 752, 590, 591, 592, 593, 594, 595, 596, 597, 598 ],
            "B": [ "0", "0" ],
            "Y": [ 753 ]
          }
        },
        "$le$designs/779/top.sv:25$19": {
          "hide_name": 1,
          "type": "$le",
          "parameters": {
            "A_SIGNED": "00000000000000000000000000000000",
            "A_WIDTH": "00000000000000000000000000000010",
            "B_SIGNED": "00000000000000000000000000000000",
            "B_WIDTH": "00000000000000000000000000000111",
            "Y_WIDTH": "00000000000000000000000000000001"
          },
          "attributes": {
            "src": "designs/779/top.sv:25.25-25.75"
          },
          "port_directions": {
            "A": "input",
            "B": "input",
            "Y": "output"
          },
          "connections": {
            "A": [ 618, 125 ],
            "B": [ 18, 19, 20, 21, 22, 23, 24 ],
            "Y": [ 743 ]
          }
        },
        "$mul$designs/779/top.sv:23$7": {
          "hide_name": 1,
          "type": "$mul",
          "parameters": {
            "A_SIGNED": "00000000000000000000000000000000",
            "A_WIDTH": "00000000000000000000000000010111",
            "B_SIGNED": "00000000000000000000000000000000",
            "B_WIDTH": "00000000000000000000000000010110",
            "Y_WIDTH": "00000000000000000000000000000010"
          },
          "attributes": {
            "src": "designs/779/top.sv:23.22-23.80"
          },
          "port_directions": {
            "A": "input",
            "B": "input",
            "Y": "output"
          },
          "connections": {
            "A": [ 71, 72, 73, 74, 75, 76, 77, 78, 79, 80, 81, 82, 83, 84, 85, 86, 87, 88, 89, 90, 91, 92, 93 ],
            "B": [ 26, 27, 28, 29, 30, 31, 32, 33, 34, 35, 36, 37, 38, 39, 40, 41, 42, 43, 44, 45, 46, 47 ],
            "Y": [ 124, 125 ]
          }
        },
        "$mul$designs/779/top.sv:24$10": {
          "hide_name": 1,
          "type": "$mul",
          "parameters": {
            "A_SIGNED": "00000000000000000000000000000000",
            "A_WIDTH": "00000000000000000000000000011001",
            "B_SIGNED": "00000000000000000000000000000000",
            "B_WIDTH": "00000000000000000000000000000111",
            "Y_WIDTH": "00000000000000000000000000011110"
          },
          "attributes": {
            "src": "designs/779/top.sv:24.25-24.71"
          },
          "port_directions": {
            "A": "input",
            "B": "input",
            "Y": "output"
          },
          "connections": {
            "A": [ 180, 181, 182, 183, 184, 185, 186, 187, 188, 189, 190, 191, 192, 193, 194, 195, 196, 197, 198, 199, 200, 201, 202, 203, 204 ],
            "B": [ 2, 3, 4, 5, 6, 7, 8 ],
            "Y": [ 754, 755, 756, 757, 758, 759, 760, 761, 762, 763, 764, 765, 766, 767, 768, 769, 770, 771, 772, 773, 774, 775, 776, 777, 778, 779, 780, 781, 782, 783 ]
          }
        },
        "$mul$designs/779/top.sv:26$25": {
          "hide_name": 1,
          "type": "$mul",
          "parameters": {
            "A_SIGNED": "00000000000000000000000000000000",
            "A_WIDTH": "00000000000000000000000000011110",
            "B_SIGNED": "00000000000000000000000000000000",
            "B_WIDTH": "00000000000000000000000000000100",
            "Y_WIDTH": "00000000000000000000000000000100"
          },
          "attributes": {
            "src": "designs/779/top.sv:26.25-26.69"
          },
          "port_directions": {
            "A": "input",
            "B": "input",
            "Y": "output"
          },
          "connections": {
            "A": [ 619, 620, 621, 622, 248, 249, 250, 251, 252, 253, 254, 255, 256, 257, 258, 259, 260, 261, 262, 263, 264, 265, 266, "0", "0", "0", "0", "0", "0", "0" ],
            "B": [ 3, 4, 5, 6 ],
            "Y": [ 576, 577, 578, 579 ]
          }
        },
        "$mul$designs/779/top.sv:29$43": {
          "hide_name": 1,
          "type": "$mul",
          "parameters": {
            "A_SIGNED": "00000000000000000000000000000000",
            "A_WIDTH": "00000000000000000000000000011110",
            "B_SIGNED": "00000000000000000000000000000000",
            "B_WIDTH": "00000000000000000000000000001011",
            "Y_WIDTH": "00000000000000000000000000011110"
          },
          "attributes": {
            "src": "designs/779/top.sv:29.24-29.90"
          },
          "port_directions": {
            "A": "input",
            "B": "input",
            "Y": "output"
          },
          "connections": {
            "A": [ 654, 655, 656, 657, 658, 659, 660, 661, "0", "0", "0", "0", "0", "0", "0", "0", "0", "0", "0", "0", "0", "0", "0", "0", "0", "0", "0", "0", "0", "0" ],
            "B": [ 244, 245, 246, 247, 248, 249, 250, 251, 252, 253, 254 ],
            "Y": [ 784, 785, 786, 787, 788, 789, 790, 791, 792, 793, 794, 795, 796, 797, 798, 799, 800, 801, 802, 803, 804, 805, 806, 807, 808, 809, 810, 811, 812, 813 ]
          }
        },
        "$mul$designs/779/top.sv:29$44": {
          "hide_name": 1,
          "type": "$mul",
          "parameters": {
            "A_SIGNED": "00000000000000000000000000000000",
            "A_WIDTH": "00000000000000000000000000011110",
            "B_SIGNED": "00000000000000000000000000000000",
            "B_WIDTH": "00000000000000000000000000000101",
            "Y_WIDTH": "00000000000000000000000000011000"
          },
          "attributes": {
            "src": "designs/779/top.sv:29.23-29.105"
          },
          "port_directions": {
            "A": "input",
            "B": "input",
            "Y": "output"
          },
          "connections": {
            "A": [ 784, 785, 786, 787, 788, 789, 790, 791, 792, 793, 794, 795, 796, 797, 798, 799, 800, 801, 802, 803, 804, 805, 806, 807, 808, 809, 810, 811, 812, 813 ],
            "B": [ 649, 650, 651, 652, 653 ],
            "Y": [ 297, 298, 299, 300, 301, 302, 303, 304, 305, 306, 307, 308, 309, 310, 311, 312, 313, 314, 315, 316, 317, 318, 319, 320 ]
          }
        },
        "$mul$designs/779/top.sv:30$47": {
          "hide_name": 1,
          "type": "$mul",
          "parameters": {
            "A_SIGNED": "00000000000000000000000000000000",
            "A_WIDTH": "00000000000000000000000000011000",
            "B_SIGNED": "00000000000000000000000000000000",
            "B_WIDTH": "00000000000000000000000000011000",
            "Y_WIDTH": "00000000000000000000000000011111"
          },
          "attributes": {
            "src": "designs/779/top.sv:30.27-30.53"
          },
          "port_directions": {
            "A": "input",
            "B": "input",
            "Y": "output"
          },
          "connections": {
            "A": [ 346, 347, 348, 349, 350, 351, 352, 353, 354, 355, 356, 357, 358, 359, 360, 361, 362, 363, 364, 365, 366, 367, 368, 369 ],
            "B": [ 321, 322, 323, 324, 325, 326, 327, 328, 329, 330, 331, 332, 333, 334, 335, 336, 337, 338, 339, 340, 341, 342, 343, 344 ],
            "Y": [ 732, 733, 734, 735, 736, 737, 738, 739, 740, 379, 380, 381, 382, 383, 384, 385, 386, 387, 388, 389, 390, 391, 392, 393, 394, 395, 396, 397, 398, 399, 400 ]
          }
        },
        "$mul$designs/779/top.sv:33$64": {
          "hide_name": 1,
          "type": "$mul",
          "parameters": {
            "A_SIGNED": "00000000000000000000000000000000",
            "A_WIDTH": "00000000000000000000000000011111",
            "B_SIGNED": "00000000000000000000000000000000",
            "B_WIDTH": "00000000000000000000000000011111",
            "Y_WIDTH": "00000000000000000000000000011111"
          },
          "attributes": {
            "src": "designs/779/top.sv:33.38-33.84"
          },
          "port_directions": {
            "A": "input",
            "B": "input",
            "Y": "output"
          },
          "connections": {
            "A": [ 463, 464, 465, 466, 467, 468, 469, 470, 471, 472, 473, 474, 475, 476, 477, 478, 479, 480, 481, 482, 483, 484, 485, 486, 487, 488, 489, 490, 491, 492, 493 ],
            "B": [ 676, 677, 678, 679, 680, 681, 682, 683, "1", "1", "1", "1", "1", "1", "1", "1", "1", "1", "1", "1", "1", "1", "1", "1", "1", "1", "1", "1", "1", "1", "1" ],
            "Y": [ 684, 685, 814, 815, 816, 817, 818, 819, 820, 821, 822, 823, 824, 825, 826, 827, 828, 829, 830, 831, 832, 833, 834, 835, 836, 837, 838, 839, 840, 841, 842 ]
          }
        },
        "$mul$designs/779/top.sv:33$66": {
          "hide_name": 1,
          "type": "$mul",
          "parameters": {
            "A_SIGNED": "00000000000000000000000000000000",
            "A_WIDTH": "00000000000000000000000000011111",
            "B_SIGNED": "00000000000000000000000000000000",
            "B_WIDTH": "00000000000000000000000000011001",
            "Y_WIDTH": "00000000000000000000000000010000"
          },
          "attributes": {
            "src": "designs/779/top.sv:33.36-33.110"
          },
          "port_directions": {
            "A": "input",
            "B": "input",
            "Y": "output"
          },
          "connections": {
            "A": [ 686, 687, 814, 815, 816, 817, 818, 819, 820, 821, 822, 823, 824, 825, 826, 827, 828, 829, 830, 831, 832, 833, 834, 835, 836, 837, 838, 839, 840, 841, 842 ],
            "B": [ 674, "0", "0", "0", "0", "0", "0", "0", "0", "0", "0", "0", "0", "0", "0", "0", "0", "0", "0", "0", "0", "0", "0", "0", "0" ],
            "Y": [ 843, 844, 845, 846, 847, 848, 849, 850, 851, 852, 853, 854, 855, 856, 857, 858 ]
          }
        },
        "$mul$designs/779/top.sv:34$73": {
          "hide_name": 1,
          "type": "$mul",
          "parameters": {
            "A_SIGNED": "00000000000000000000000000000000",
            "A_WIDTH": "00000000000000000000000000000001",
            "B_SIGNED": "00000000000000000000000000000000",
            "B_WIDTH": "00000000000000000000000000011001",
            "Y_WIDTH": "00000000000000000000000000011001"
          },
          "attributes": {
            "src": "designs/779/top.sv:34.26-34.67"
          },
          "port_directions": {
            "A": "input",
            "B": "input",
            "Y": "output"
          },
          "connections": {
            "A": [ 753 ],
            "B": [ 688, "1", "1", "1", "1", "1", "1", "1", "1", "1", "1", "1", "1", "1", "1", "1", "1", "1", "1", "1", "1", "1", "1", "1", "1" ],
            "Y": [ 494, 495, 496, 497, 498, 499, 500, 501, 502, 503, 504, 505, 506, 507, 508, 509, 510, 511, 512, 513, 514, 515, 516, 517, 518 ]
          }
        },
        "$mul$designs/779/top.sv:34$77": {
          "hide_name": 1,
          "type": "$mul",
          "parameters": {
            "A_SIGNED": "00000000000000000000000000000000",
            "A_WIDTH": "00000000000000000000000000011001",
            "B_SIGNED": "00000000000000000000000000000000",
            "B_WIDTH": "00000000000000000000000000011001",
            "Y_WIDTH": "00000000000000000000000000001001"
          },
          "attributes": {
            "src": "designs/779/top.sv:34.24-34.96"
          },
          "port_directions": {
            "A": "input",
            "B": "input",
            "Y": "output"
          },
          "connections": {
            "A": [ 519, 520, 521, 522, 523, 524, 525, 526, 527, 528, 529, 530, 531, 532, 533, 534, 535, 536, 537, 538, 539, 540, 541, 542, 543 ],
            "B": [ 689, 690, 691, 692, 693, 694, 695, 696, 697, 698, 699, "1", "1", "1", "1", "1", "1", "1", "1", "1", "1", "1", "1", "1", "1" ],
            "Y": [ 581, 582, 583, 584, 585, 586, 587, 588, 589 ]
          }
        },
        "$ne$designs/779/top.sv:25$21": {
          "hide_name": 1,
          "type": "$ne",
          "parameters": {
            "A_SIGNED": "00000000000000000000000000000000",
            "A_WIDTH": "00000000000000000000000000000001",
            "B_SIGNED": "00000000000000000000000000000000",
            "B_WIDTH": "00000000000000000000000000010111",
            "Y_WIDTH": "00000000000000000000000000000001"
          },
          "attributes": {
            "src": "designs/779/top.sv:25.23-25.96"
          },
          "port_directions": {
            "A": "input",
            "B": "input",
            "Y": "output"
          },
          "connections": {
            "A": [ 744 ],
            "B": [ 25, 26, 27, 28, 29, 30, 31, 32, 33, 34, 35, 36, 37, 38, 39, 40, 41, 42, 43, 44, 45, 46, 47 ],
            "Y": [ 745 ]
          }
        },
        "$not$designs/779/top.sv:36$81": {
          "hide_name": 1,
          "type": "$not",
          "parameters": {
            "A_SIGNED": "00000000000000000000000000000000",
            "A_WIDTH": "00000000000000000000000000010000",
            "Y_WIDTH": "00000000000000000000000000010000"
          },
          "attributes": {
            "src": "designs/779/top.sv:36.82-36.89"
          },
          "port_directions": {
            "A": "input",
            "Y": "output"
          },
          "connections": {
            "A": [ 244, 245, 246, 247, 248, 249, 250, 251, 252, 253, 254, 255, 256, 257, 258, 259 ],
            "Y": [ 544, 545, 546, 547, 548, 549, 550, 551, 552, 553, 554, 555, 556, 557, 558, 559 ]
          }
        },
        "$or$designs/779/top.sv:28$33": {
          "hide_name": 1,
          "type": "$or",
          "parameters": {
            "A_SIGNED": "00000000000000000000000000000000",
            "A_WIDTH": "00000000000000000000000000001000",
            "B_SIGNED": "00000000000000000000000000000000",
            "B_WIDTH": "00000000000000000000000000001000",
            "Y_WIDTH": "00000000000000000000000000001000"
          },
          "attributes": {
            "src": "designs/779/top.sv:28.25-28.47"
          },
          "port_directions": {
            "A": "input",
            "B": "input",
            "Y": "output"
          },
          "connections": {
            "A": [ 244, 245, 246, 247, 248, 249, 250, 251 ],
            "B": [ 257, 258, 259, 260, 261, 262, 263, 264 ],
            "Y": [ 859, 860, 861, 862, 863, 864, 865, 866 ]
          }
        },
        "$or$designs/779/top.sv:28$35": {
          "hide_name": 1,
          "type": "$or",
          "parameters": {
            "A_SIGNED": "00000000000000000000000000000000",
            "A_WIDTH": "00000000000000000000000000001000",
            "B_SIGNED": "00000000000000000000000000000000",
            "B_WIDTH": "00000000000000000000000000001000",
            "Y_WIDTH": "00000000000000000000000000001000"
          },
          "attributes": {
            "src": "designs/779/top.sv:28.23-28.67"
          },
          "port_directions": {
            "A": "input",
            "B": "input",
            "Y": "output"
          },
          "connections": {
            "A": [ 867, 868, 869, 870, 871, 872, 873, 874 ],
            "B": [ 244, 245, 246, 247, 248, 249, 250, 251 ],
            "Y": [ 875, 876, 877, 878, 879, 880, 881, 882 ]
          }
        },
        "$reduce_bool$designs/779/top.sv:33$67": {
          "hide_name": 1,
          "type": "$reduce_bool",
          "parameters": {
            "A_SIGNED": "00000000000000000000000000000000",
            "A_WIDTH": "00000000000000000000000000000100",
            "Y_WIDTH": "00000000000000000000000000000001"
          },
          "attributes": {
            "src": "designs/779/top.sv:33.21-33.131"
          },
          "port_directions": {
            "A": "input",
            "Y": "output"
          },
          "connections": {
            "A": [ 244, 245, 246, 247 ],
            "Y": [ 883 ]
          }
        },
        "$sub$designs/779/top.sv:23$5": {
          "hide_name": 1,
          "type": "$sub",
          "parameters": {
            "A_SIGNED": "00000000000000000000000000000000",
            "A_WIDTH": "00000000000000000000000000010111",
            "B_SIGNED": "00000000000000000000000000000000",
            "B_WIDTH": "00000000000000000000000000000010",
            "Y_WIDTH": "00000000000000000000000000010111"
          },
          "attributes": {
            "src": "designs/779/top.sv:23.24-23.48"
          },
          "port_directions": {
            "A": "input",
            "B": "input",
            "Y": "output"
          },
          "connections": {
            "A": [ 25, 26, 27, 28, 29, 30, 31, 32, 33, 34, 35, 36, 37, 38, 39, 40, 41, 42, 43, 44, 45, 46, 47 ],
            "B": [ 4, 5 ],
            "Y": [ 48, 49, 50, 51, 52, 53, 54, 55, 56, 57, 58, 59, 60, 61, 62, 63, 64, 65, 66, 67, 68, 69, 70 ]
          }
        },
        "$sub$designs/779/top.sv:24$13": {
          "hide_name": 1,
          "type": "$sub",
          "parameters": {
            "A_SIGNED": "00000000000000000000000000000000",
            "A_WIDTH": "00000000000000000000000000011110",
            "B_SIGNED": "00000000000000000000000000000000",
            "B_WIDTH": "00000000000000000000000000011110",
            "Y_WIDTH": "00000000000000000000000000011110"
          },
          "attributes": {
            "src": "designs/779/top.sv:24.24-24.88"
          },
          "port_directions": {
            "A": "input",
            "B": "input",
            "Y": "output"
          },
          "connections": {
            "A": [ 754, 755, 756, 757, 758, 759, 760, 761, 762, 763, 764, 765, 766, 767, 768, 769, 770, 771, 772, 773, 774, 775, 776, 777, 778, 779, 780, 781, 782, 783 ],
            "B": [ 18, 19, 20, 21, 22, 23, 24, "1", "1", "1", "1", "1", "1", "1", "1", "1", "1", "1", "1", "1", "1", "1", "1", "1", "1", "1", "1", "1", "1", "1" ],
            "Y": [ 94, 95, 96, 97, 98, 99, 100, 101, 102, 103, 104, 105, 106, 107, 108, 109, 110, 111, 112, 113, 114, 115, 116, 117, 118, 119, 120, 121, 122, 123 ]
          }
        },
        "$sub$designs/779/top.sv:28$34": {
          "hide_name": 1,
          "type": "$sub",
          "parameters": {
            "A_SIGNED": "00000000000000000000000000000000",
            "A_WIDTH": "00000000000000000000000000001000",
            "B_SIGNED": "00000000000000000000000000000000",
            "B_WIDTH": "00000000000000000000000000001000",
            "Y_WIDTH": "00000000000000000000000000001000"
          },
          "attributes": {
            "src": "designs/779/top.sv:28.24-28.57"
          },
          "port_directions": {
            "A": "input",
            "B": "input",
            "Y": "output"
          },
          "connections": {
            "A": [ 859, 860, 861, 862, 863, 864, 865, 866 ],
            "B": [ 244, 245, 246, 247, 248, 249, 250, 251 ],
            "Y": [ 867, 868, 869, 870, 871, 872, 873, 874 ]
          }
        },
        "$sub$designs/779/top.sv:28$36": {
          "hide_name": 1,
          "type": "$sub",
          "parameters": {
            "A_SIGNED": "00000000000000000000000000000000",
            "A_WIDTH": "00000000000000000000000000001000",
            "B_SIGNED": "00000000000000000000000000000000",
            "B_WIDTH": "00000000000000000000000000000001",
            "Y_WIDTH": "00000000000000000000000000001000"
          },
          "attributes": {
            "src": "designs/779/top.sv:28.22-28.77"
          },
          "port_directions": {
            "A": "input",
            "B": "input",
            "Y": "output"
          },
          "connections": {
            "A": [ 875, 876, 877, 878, 879, 880, 881, 882 ],
            "B": [ 345 ],
            "Y": [ 646, 647, 648, 649, 650, 651, 652, 653 ]
          }
        },
        "$sub$designs/779/top.sv:29$39": {
          "hide_name": 1,
          "type": "$sub",
          "parameters": {
            "A_SIGNED": "00000000000000000000000000000000",
            "A_WIDTH": "00000000000000000000000000000111",
            "B_SIGNED": "00000000000000000000000000000000",
            "B_WIDTH": "00000000000000000000000000011110",
            "Y_WIDTH": "00000000000000000000000000011110"
          },
          "attributes": {
            "src": "designs/779/top.sv:29.28-29.50"
          },
          "port_directions": {
            "A": "input",
            "B": "input",
            "Y": "output"
          },
          "connections": {
            "A": [ 2, 3, 4, 5, 6, 7, 8 ],
            "B": [ 623, 624, 625, 626, 627, 628, 629, 630, 631, 632, 633, 634, 635, 636, 637, 638, 639, 640, 641, 642, 643, 644, 645, "1", "1", "1", "1", "1", "1", "1" ],
            "Y": [ 884, 885, 886, 887, 888, 889, 890, 891, 892, 893, 894, 895, 896, 897, 898, 899, 900, 901, 902, 903, 904, 905, 906, 907, 908, 909, 910, 911, 912, 913 ]
          }
        },
        "$sub$designs/779/top.sv:29$40": {
          "hide_name": 1,
          "type": "$sub",
          "parameters": {
            "A_SIGNED": "00000000000000000000000000000000",
            "A_WIDTH": "00000000000000000000000000011110",
            "B_SIGNED": "00000000000000000000000000000000",
            "B_WIDTH": "00000000000000000000000000010111",
            "Y_WIDTH": "00000000000000000000000000011110"
          },
          "attributes": {
            "src": "designs/779/top.sv:29.27-29.60"
          },
          "port_directions": {
            "A": "input",
            "B": "input",
            "Y": "output"
          },
          "connections": {
            "A": [ 884, 885, 886, 887, 888, 889, 890, 891, 892, 893, 894, 895, 896, 897, 898, 899, 900, 901, 902, 903, 904, 905, 906, 907, 908, 909, 910, 911, 912, 913 ],
            "B": [ 25, 26, 27, 28, 29, 30, 31, 32, 33, 34, 35, 36, 37, 38, 39, 40, 41, 42, 43, 44, 45, 46, 47 ],
            "Y": [ 214, 215, 216, 217, 218, 219, 220, 221, 222, 223, 224, 225, 226, 227, 228, 229, 230, 231, 232, 233, 234, 235, 236, 237, 238, 239, 240, 241, 242, 243 ]
          }
        },
        "$sub$designs/779/top.sv:30$53": {
          "hide_name": 1,
          "type": "$sub",
          "parameters": {
            "A_SIGNED": "00000000000000000000000000000000",
            "A_WIDTH": "00000000000000000000000000011111",
            "B_SIGNED": "00000000000000000000000000000000",
            "B_WIDTH": "00000000000000000000000000000111",
            "Y_WIDTH": "00000000000000000000000000011111"
          },
          "attributes": {
            "src": "designs/779/top.sv:30.23-30.105"
          },
          "port_directions": {
            "A": "input",
            "B": "input",
            "Y": "output"
          },
          "connections": {
            "A": [ 671, 672, "0", "0", "0", "0", "0", "0", "0", "0", "0", "0", "0", "0", "0", "0", "0", "0", "0", "0", "0", "0", "0", "0", "0", "0", "0", "0", "0", "0", "0" ],
            "B": [ 2, 3, 4, 5, 6, 7, 8 ],
            "Y": [ 673, 914, 915, 916, 917, 918, 919, 920, 921, 922, 923, 924, 925, 926, 927, 928, 929, 930, 931, 932, 933, 934, 935, 936, 937, 938, 939, 940, 941, 942, 943 ]
          }
        },
        "$sub$designs/779/top.sv:33$60": {
          "hide_name": 1,
          "type": "$sub",
          "parameters": {
            "A_SIGNED": "00000000000000000000000000000000",
            "A_WIDTH": "00000000000000000000000000000110",
            "B_SIGNED": "00000000000000000000000000000000",
            "B_WIDTH": "00000000000000000000000000011111",
            "Y_WIDTH": "00000000000000000000000000011111"
          },
          "attributes": {
            "src": "designs/779/top.sv:33.40-33.61"
          },
          "port_directions": {
            "A": "input",
            "B": "input",
            "Y": "output"
          },
          "connections": {
            "A": [ 249, 250, 251, 252, 253, 254 ],
            "B": [ 674, "0", "0", "0", "0", "0", "0", "0", "0", "0", "0", "0", "0", "0", "0", "0", "0", "0", "0", "0", "0", "0", "0", "0", "0", "0", "0", "0", "0", "0", "0" ],
            "Y": [ 432, 433, 434, 435, 436, 437, 438, 439, 440, 441, 442, 443, 444, 445, 446, 447, 448, 449, 450, 451, 452, 453, 454, 455, 456, 457, 458, 459, 460, 461, 462 ]
          }
        },
        "$ternary$designs/779/top.sv:33$69": {
          "hide_name": 1,
          "type": "$mux",
          "parameters": {
            "WIDTH": "00000000000000000000000000010000"
          },
          "attributes": {
            "src": "designs/779/top.sv:33.21-33.131"
          },
          "port_directions": {
            "A": "input",
            "B": "input",
            "S": "input",
            "Y": "output"
          },
          "connections": {
            "A": [ 742, "1", "1", "1", "1", "1", "1", "1", "1", "1", "1", "1", "1", "1", "1", "1" ],
            "B": [ 843, 844, 845, 846, 847, 848, 849, 850, 851, 852, 853, 854, 855, 856, 857, 858 ],
            "S": [ 883 ],
            "Y": [ 746, 747, 748, 749, 750, 751, 752, 590, 591, 592, 593, 594, 595, 596, 597, 598 ]
          }
        },
        "$ternary$designs/779/top.sv:36$85": {
          "hide_name": 1,
          "type": "$mux",
          "parameters": {
            "WIDTH": "00000000000000000000000000010000"
          },
          "attributes": {
            "src": "designs/779/top.sv:36.22-36.101"
          },
          "port_directions": {
            "A": "input",
            "B": "input",
            "S": "input",
            "Y": "output"
          },
          "connections": {
            "A": [ 701, 702, 703, 704, 705, 706, 707, 708, 568, 569, 570, 571, 572, 573, 574, 575 ],
            "B": [ 700, 322, 323, 324, 325, 326, 327, 328, 329, "0", "0", "0", "0", "0", "0", "0" ],
            "S": [ 674 ],
            "Y": [ 608, 609, 610, 611, 612, 613, 614, 615, 616, 944, 945, 946, 947, 948, 949, 950 ]
          }
        }
      },
      "netnames": {
        "$add$designs/779/top.sv:23$6_Y": {
          "hide_name": 1,
          "bits": [ 71, 72, 73, 74, 75, 76, 77, 78, 79, 80, 81, 82, 83, 84, 85, 86, 87, 88, 89, 90, 91, 92, 93 ],
          "attributes": {
            "src": "designs/779/top.sv:23.23-23.64"
          }
        },
        "$add$designs/779/top.sv:24$14_Y": {
          "hide_name": 1,
          "bits": [ 126, 127, 128, 129, 130, 131, 132, 133, 134, 135, 136, 137, 138, 139, 140, 141, 142, 143, 144, 145, 146, 147, 148, 149, 150, 151, 152, 153, 154, 155 ],
          "attributes": {
            "src": "designs/779/top.sv:24.23-24.103",
            "unused_bits": "23 24 25 26 27 28 29"
          }
        },
        "$add$designs/779/top.sv:24$8_Y": {
          "hide_name": 1,
          "bits": [ 156, 157, 158, 159, 160, 161, 162, 163, 164, 165, 166, 167, 168, 169, 170, 171, 172, 173, 174, 175, 176, 177, 178, 179, "0", "0", "0", "0", "0", "0" ],
          "attributes": {
            "src": "designs/779/top.sv:24.27-24.42"
          }
        },
        "$add$designs/779/top.sv:24$9_Y": {
          "hide_name": 1,
          "bits": [ 180, 181, 182, 183, 184, 185, 186, 187, 188, 189, 190, 191, 192, 193, 194, 195, 196, 197, 198, 199, 200, 201, 202, 203, 204, "0", "0", "0", "0", "0" ],
          "attributes": {
            "src": "designs/779/top.sv:24.26-24.57"
          }
        },
        "$add$designs/779/top.sv:29$41_Y": {
          "hide_name": 1,
          "bits": [ 267, 268, 269, 270, 271, 272, 273, 274, 275, 276, 277, 278, 279, 280, 281, 282, 283, 284, 285, 286, 287, 288, 289, 290, 291, 292, 293, 294, 295, 296 ],
          "attributes": {
            "src": "designs/779/top.sv:29.26-29.70",
            "unused_bits": "8 9 10 11 12 13 14 15 16 17 18 19 20 21 22 23 24 25 26 27 28 29"
          }
        },
        "$add$designs/779/top.sv:30$46_Y": {
          "hide_name": 1,
          "bits": [ 346, 347, 348, 349, 350, 351, 352, 353, 354, 355, 356, 357, 358, 359, 360, 361, 362, 363, 364, 365, 366, 367, 368, 369, "0", "0", "0", "0", "0", "0", "0" ],
          "attributes": {
            "src": "designs/779/top.sv:30.28-30.43"
          }
        },
        "$add$designs/779/top.sv:30$51_Y": {
          "hide_name": 1,
          "bits": [ 401, 402, 403, 404, 405, 406, 407, 408, 409, 410, 411, 412, 413, 414, 415, 416, 417, 418, 419, 420, 421, 422, 423, 424, 425, 426, 427, 428, 429, 430, 431 ],
          "attributes": {
            "src": "designs/779/top.sv:30.25-30.81",
            "unused_bits": "2 3 4 5 6 7 8 9 10 11 12 13 14 15 16 17 18 19 20 21 22 23 24 25 26 27 28 29 30"
          }
        },
        "$add$designs/779/top.sv:33$61_Y": {
          "hide_name": 1,
          "bits": [ 463, 464, 465, 466, 467, 468, 469, 470, 471, 472, 473, 474, 475, 476, 477, 478, 479, 480, 481, 482, 483, 484, 485, 486, 487, 488, 489, 490, 491, 492, 493 ],
          "attributes": {
            "src": "designs/779/top.sv:33.39-33.71"
          }
        },
        "$add$designs/779/top.sv:34$74_Y": {
          "hide_name": 1,
          "bits": [ 519, 520, 521, 522, 523, 524, 525, 526, 527, 528, 529, 530, 531, 532, 533, 534, 535, 536, 537, 538, 539, 540, 541, 542, 543 ],
          "attributes": {
            "src": "designs/779/top.sv:34.25-34.83"
          }
        },
        "$add$designs/779/top.sv:36$82_Y": {
          "hide_name": 1,
          "bits": [ 560, 561, 562, 563, 564, 565, 566, 567, 568, 569, 570, 571, 572, 573, 574, 575 ],
          "attributes": {
          }
        },
        "$and$designs/779/top.sv:26$26_Y": {
          "hide_name": 1,
          "bits": [ 580, 206, 207, 208, 951, 952, 953, 954, 955, 956, 957, 958, 959, 960, 961, 962, 963, 964, 965, 966, 967, 968, 969, 970, 971, 972, 973, 974, 975, 976 ],
          "attributes": {
            "src": "designs/779/top.sv:26.24-26.79",
            "unused_bits": "4 5 6 7 8 9 10 11 12 13 14 15 16 17 18 19 20 21 22 23 24 25 26 27 28 29"
          }
        },
        "$and$designs/779/top.sv:29$42_Y": {
          "hide_name": 1,
          "bits": [ 654, 655, 656, 657, 658, 659, 660, 661, "0", "0", "0", "0", "0", "0", "0", "0", "0", "0", "0", "0", "0", "0", "0", "0", "0", "0", "0", "0", "0", "0" ],
          "attributes": {
            "src": "designs/779/top.sv:29.25-29.80"
          }
        },
        "$and$designs/779/top.sv:30$50_Y": {
          "hide_name": 1,
          "bits": [ 370, 371, 372, 373, 374, 375, 376, 377, 378, 379, 380, 381, 382, 383, 384, 385, 386, 387, 388, 389, 390, 391, 392, 393, 394, 395, 396, 397, 398, 399, 400 ],
          "attributes": {
            "src": "designs/779/top.sv:30.26-30.71"
          }
        },
        "$and$designs/779/top.sv:30$52_Y": {
          "hide_name": 1,
          "bits": [ 671, 672, "0", "0", "0", "0", "0", "0", "0", "0", "0", "0", "0", "0", "0", "0", "0", "0", "0", "0", "0", "0", "0", "0", "0", "0", "0", "0", "0", "0", "0" ],
          "attributes": {
            "src": "designs/779/top.sv:30.24-30.91"
          }
        },
        "$and$designs/779/top.sv:32$55_Y": {
          "hide_name": 1,
          "bits": [ 675, "0", "0", "0", "0", "0", "0", "0", "0", "0", "0", "0", "0", "0", "0", "0", "0", "0", "0" ],
          "attributes": {
            "src": "designs/779/top.sv:32.29-32.51"
          }
        },
        "$and$designs/779/top.sv:32$56_Y": {
          "hide_name": 1,
          "bits": [ 741, "0", "0", "0", "0", "0", "0", "0", "0", "0", "0", "0", "0", "0", "0", "0", "0", "0", "0" ],
          "attributes": {
            "src": "designs/779/top.sv:32.28-32.61"
          }
        },
        "$auto$opt_expr.cc:205:group_cell_inputs$104": {
          "hide_name": 1,
          "bits": [ 18, 19, 20, 21, 22, 23, 24 ],
          "attributes": {
          }
        },
        "$auto$opt_expr.cc:205:group_cell_inputs$116": {
          "hide_name": 1,
          "bits": [ 618 ],
          "attributes": {
          }
        },
        "$auto$opt_expr.cc:205:group_cell_inputs$119": {
          "hide_name": 1,
          "bits": [ 619, 620, 621, 622 ],
          "attributes": {
          }
        },
        "$auto$opt_expr.cc:205:group_cell_inputs$122": {
          "hide_name": 1,
          "bits": [ 205 ],
          "attributes": {
          }
        },
        "$auto$opt_expr.cc:205:group_cell_inputs$125": {
          "hide_name": 1,
          "bits": [ 209 ],
          "attributes": {
          }
        },
        "$auto$opt_expr.cc:205:group_cell_inputs$129": {
          "hide_name": 1,
          "bits": [ 623, 624, 625, 626, 627, 628, 629, 630, 631, 632, 633, 634, 635, 636, 637, 638, 639, 640, 641, 642, 643, 644, 645 ],
          "attributes": {
          }
        },
        "$auto$opt_expr.cc:205:group_cell_inputs$137": {
          "hide_name": 1,
          "bits": [ 662, 663, 664, 665, 666, 667, 668, 669, 670 ],
          "attributes": {
          }
        },
        "$auto$opt_expr.cc:205:group_cell_inputs$164": {
          "hide_name": 1,
          "bits": [ 676, 677, 678, 679, 680, 681, 682, 683 ],
          "attributes": {
          }
        },
        "$auto$opt_expr.cc:205:group_cell_inputs$168": {
          "hide_name": 1,
          "bits": [ 686, 687 ],
          "attributes": {
          }
        },
        "$auto$opt_expr.cc:205:group_cell_inputs$170": {
          "hide_name": 1,
          "bits": [ 814, 815, 816, 817, 818, 819, 820, 821, 822, 823, 824, 825, 826, 827, 828, 829, 830, 831, 832, 833, 834, 835, 836, 837, 838, 839, 840, 841, 842 ],
          "attributes": {
          }
        },
        "$auto$opt_expr.cc:205:group_cell_inputs$171": {
          "hide_name": 1,
          "bits": [ 688 ],
          "attributes": {
          }
        },
        "$auto$opt_expr.cc:205:group_cell_inputs$175": {
          "hide_name": 1,
          "bits": [ 689, 690, 691, 692, 693, 694, 695, 696, 697, 698, 699 ],
          "attributes": {
          }
        },
        "$auto$opt_expr.cc:205:group_cell_inputs$179": {
          "hide_name": 1,
          "bits": [ 700 ],
          "attributes": {
          }
        },
        "$auto$opt_expr.cc:205:group_cell_inputs$182": {
          "hide_name": 1,
          "bits": [ 701, 702, 703, 704, 705, 706, 707, 708 ],
          "attributes": {
          }
        },
        "$auto$opt_expr.cc:205:group_cell_inputs$191": {
          "hide_name": 1,
          "bits": [ 709, 710, 711, 712, 713, 714, 715, 716, 717, 718, 719, 720, 721, 722, 723, 724, 725, 726, 727, 728, 729, 730, 731 ],
          "attributes": {
          }
        },
        "$auto$wreduce.cc:514:run$101": {
          "hide_name": 1,
          "bits": [ 581, 582, 583, 584, 585, 586, 587, 588, 589, 977, 978, 979, 980, 981, 982, 983, 984, 985, 986, 987, 988, 989, 990, 991, 992 ],
          "attributes": {
            "src": "designs/779/top.sv:34.24-34.96",
            "unused_bits": "9 10 11 12 13 14 15 16 17 18 19 20 21 22 23 24"
          }
        },
        "$auto$wreduce.cc:514:run$99": {
          "hide_name": 1,
          "bits": [ 544, 545, 546, 547, 548, 549, 550, 551, 552, 553, 554, 555, 556, 557, 558, 559, 993, 994, 995, 996, 997, 998, 999, 1000, 1001, 1002, 1003, 1004, 1005, 1006 ],
          "attributes": {
            "src": "designs/779/top.sv:36.82-36.89",
            "unused_bits": "16 17 18 19 20 21 22 23 24 25 26 27 28 29"
          }
        },
        "$ge$designs/779/top.sv:25$16_Y": {
          "hide_name": 1,
          "bits": [ 617, "0", "0", "0", "0", "0", "0" ],
          "attributes": {
            "src": "designs/779/top.sv:25.27-25.47"
          }
        },
        "$gt$designs/779/top.sv:25$20_Y": {
          "hide_name": 1,
          "bits": [ 744, "0", "0", "0", "0", "0", "0", "0", "0", "0", "0", "0", "0", "0", "0", "0", "0", "0", "0", "0", "0", "0", "0" ],
          "attributes": {
            "src": "designs/779/top.sv:25.24-25.85"
          }
        },
        "$gt$designs/779/top.sv:34$70_Y": {
          "hide_name": 1,
          "bits": [ 753, "0", "0", "0", "0", "0", "0", "0", "0", "0", "0", "0", "0", "0", "0", "0", "0", "0", "0", "0", "0", "0", "0", "0", "0" ],
          "attributes": {
            "src": "designs/779/top.sv:34.27-34.49"
          }
        },
        "$le$designs/779/top.sv:25$19_Y": {
          "hide_name": 1,
          "bits": [ 743, "0", "0", "0", "0", "0", "0", "0", "0", "0", "0", "0", "0", "0", "0", "0", "0", "0", "0", "0", "0", "0", "0", "0", "0", "0", "0", "0", "0", "0" ],
          "attributes": {
            "src": "designs/779/top.sv:25.25-25.75"
          }
        },
        "$mul$designs/779/top.sv:24$10_Y": {
          "hide_name": 1,
          "bits": [ 754, 755, 756, 757, 758, 759, 760, 761, 762, 763, 764, 765, 766, 767, 768, 769, 770, 771, 772, 773, 774, 775, 776, 777, 778, 779, 780, 781, 782, 783 ],
          "attributes": {
            "src": "designs/779/top.sv:24.25-24.71"
          }
        },
        "$mul$designs/779/top.sv:26$25_Y": {
          "hide_name": 1,
          "bits": [ 576, 577, 578, 579, 1007, 1008, 1009, 1010, 1011, 1012, 1013, 1014, 1015, 1016, 1017, 1018, 1019, 1020, 1021, 1022, 1023, 1024, 1025, 1026, 1027, 1028, 1029, 1030, 1031, 1032 ],
          "attributes": {
            "src": "designs/779/top.sv:26.25-26.69",
            "unused_bits": "4 5 6 7 8 9 10 11 12 13 14 15 16 17 18 19 20 21 22 23 24 25 26 27 28 29"
          }
        },
        "$mul$designs/779/top.sv:29$43_Y": {
          "hide_name": 1,
          "bits": [ 784, 785, 786, 787, 788, 789, 790, 791, 792, 793, 794, 795, 796, 797, 798, 799, 800, 801, 802, 803, 804, 805, 806, 807, 808, 809, 810, 811, 812, 813 ],
          "attributes": {
            "src": "designs/779/top.sv:29.24-29.90"
          }
        },
        "$mul$designs/779/top.sv:29$44_Y": {
          "hide_name": 1,
          "bits": [ 297, 298, 299, 300, 301, 302, 303, 304, 305, 306, 307, 308, 309, 310, 311, 312, 313, 314, 315, 316, 317, 318, 319, 320, 1033, 1034, 1035, 1036, 1037, 1038 ],
          "attributes": {
            "src": "designs/779/top.sv:29.23-29.105",
            "unused_bits": "24 25 26 27 28 29"
          }
        },
        "$mul$designs/779/top.sv:30$47_Y": {
          "hide_name": 1,
          "bits": [ 732, 733, 734, 735, 736, 737, 738, 739, 740, 379, 380, 381, 382, 383, 384, 385, 386, 387, 388, 389, 390, 391, 392, 393, 394, 395, 396, 397, 398, 399, 400 ],
          "attributes": {
            "src": "designs/779/top.sv:30.27-30.53"
          }
        },
        "$mul$designs/779/top.sv:33$64_Y": {
          "hide_name": 1,
          "bits": [ 684, 685, 814, 815, 816, 817, 818, 819, 820, 821, 822, 823, 824, 825, 826, 827, 828, 829, 830, 831, 832, 833, 834, 835, 836, 837, 838, 839, 840, 841, 842 ],
          "attributes": {
            "src": "designs/779/top.sv:33.38-33.84"
          }
        },
        "$mul$designs/779/top.sv:33$66_Y": {
          "hide_name": 1,
          "bits": [ 843, 844, 845, 846, 847, 848, 849, 850, 851, 852, 853, 854, 855, 856, 857, 858, 1039, 1040, 1041, 1042, 1043, 1044, 1045, 1046, 1047, 1048, 1049, 1050, 1051, 1052, 1053 ],
          "attributes": {
            "src": "designs/779/top.sv:33.36-33.110",
            "unused_bits": "16 17 18 19 20 21 22 23 24 25 26 27 28 29 30"
          }
        },
        "$mul$designs/779/top.sv:34$73_Y": {
          "hide_name": 1,
          "bits": [ 494, 495, 496, 497, 498, 499, 500, 501, 502, 503, 504, 505, 506, 507, 508, 509, 510, 511, 512, 513, 514, 515, 516, 517, 518 ],
          "attributes": {
            "src": "designs/779/top.sv:34.26-34.67"
          }
        },
        "$ne$designs/779/top.sv:25$21_Y": {
          "hide_name": 1,
          "bits": [ 745, "0", "0", "0", "0", "0", "0", "0", "0", "0", "0", "0", "0", "0", "0", "0", "0", "0", "0", "0", "0", "0", "0", "0", "0", "0", "0", "0", "0", "0" ],
          "attributes": {
            "src": "designs/779/top.sv:25.23-25.96"
          }
        },
        "$or$designs/779/top.sv:28$33_Y": {
          "hide_name": 1,
          "bits": [ 859, 860, 861, 862, 863, 864, 865, 866, 1054, 1055, 1056, 1057, 1058, 1059, 1060, 1061, 1062, 1063, 1064, 1065, 1066, 1067, 1068, 1069, 1070, 1071, 1072, 1073, 1074, 1075 ],
          "attributes": {
            "src": "designs/779/top.sv:28.25-28.47",
            "unused_bits": "8 9 10 11 12 13 14 15 16 17 18 19 20 21 22 23 24 25 26 27 28 29"
          }
        },
        "$or$designs/779/top.sv:28$35_Y": {
          "hide_name": 1,
          "bits": [ 875, 876, 877, 878, 879, 880, 881, 882, 1076, 1077, 1078, 1079, 1080, 1081, 1082, 1083, 1084, 1085, 1086, 1087, 1088, 1089, 1090, 1091, 1092, 1093, 1094, 1095, 1096, 1097 ],
          "attributes": {
            "src": "designs/779/top.sv:28.23-28.67",
            "unused_bits": "8 9 10 11 12 13 14 15 16 17 18 19 20 21 22 23 24 25 26 27 28 29"
          }
        },
        "$reduce_bool$designs/779/top.sv:33$67_Y": {
          "hide_name": 1,
          "bits": [ 883 ],
          "attributes": {
            "src": "designs/779/top.sv:33.21-33.131"
          }
        },
        "$sub$designs/779/top.sv:23$5_Y": {
          "hide_name": 1,
          "bits": [ 48, 49, 50, 51, 52, 53, 54, 55, 56, 57, 58, 59, 60, 61, 62, 63, 64, 65, 66, 67, 68, 69, 70 ],
          "attributes": {
            "src": "designs/779/top.sv:23.24-23.48"
          }
        },
        "$sub$designs/779/top.sv:24$13_Y": {
          "hide_name": 1,
          "bits": [ 94, 95, 96, 97, 98, 99, 100, 101, 102, 103, 104, 105, 106, 107, 108, 109, 110, 111, 112, 113, 114, 115, 116, 117, 118, 119, 120, 121, 122, 123 ],
          "attributes": {
            "src": "designs/779/top.sv:24.24-24.88"
          }
        },
        "$sub$designs/779/top.sv:28$34_Y": {
          "hide_name": 1,
          "bits": [ 867, 868, 869, 870, 871, 872, 873, 874, 1098, 1099, 1100, 1101, 1102, 1103, 1104, 1105, 1106, 1107, 1108, 1109, 1110, 1111, 1112, 1113, 1114, 1115, 1116, 1117, 1118, 1119 ],
          "attributes": {
            "src": "designs/779/top.sv:28.24-28.57",
            "unused_bits": "8 9 10 11 12 13 14 15 16 17 18 19 20 21 22 23 24 25 26 27 28 29"
          }
        },
        "$sub$designs/779/top.sv:29$39_Y": {
          "hide_name": 1,
          "bits": [ 884, 885, 886, 887, 888, 889, 890, 891, 892, 893, 894, 895, 896, 897, 898, 899, 900, 901, 902, 903, 904, 905, 906, 907, 908, 909, 910, 911, 912, 913 ],
          "attributes": {
            "src": "designs/779/top.sv:29.28-29.50"
          }
        },
        "$sub$designs/779/top.sv:29$40_Y": {
          "hide_name": 1,
          "bits": [ 214, 215, 216, 217, 218, 219, 220, 221, 222, 223, 224, 225, 226, 227, 228, 229, 230, 231, 232, 233, 234, 235, 236, 237, 238, 239, 240, 241, 242, 243 ],
          "attributes": {
            "src": "designs/779/top.sv:29.27-29.60"
          }
        },
        "$sub$designs/779/top.sv:30$53_Y": {
          "hide_name": 1,
          "bits": [ 673, 914, 915, 916, 917, 918, 919, 920, 921, 922, 923, 924, 925, 926, 927, 928, 929, 930, 931, 932, 933, 934, 935, 936, 937, 938, 939, 940, 941, 942, 943 ],
          "attributes": {
            "src": "designs/779/top.sv:30.23-30.105",
            "unused_bits": "1 2 3 4 5 6 7 8 9 10 11 12 13 14 15 16 17 18 19 20 21 22 23 24 25 26 27 28 29 30"
          }
        },
        "$sub$designs/779/top.sv:33$60_Y": {
          "hide_name": 1,
          "bits": [ 432, 433, 434, 435, 436, 437, 438, 439, 440, 441, 442, 443, 444, 445, 446, 447, 448, 449, 450, 451, 452, 453, 454, 455, 456, 457, 458, 459, 460, 461, 462 ],
          "attributes": {
            "src": "designs/779/top.sv:33.40-33.61"
          }
        },
        "expr_932454": {
          "hide_name": 0,
          "bits": [ 742, "1", "1", "1", "1", "1", "1", "1", "1", "1", "1", "1", "1", "1", "1", "1", "x", "x", "x" ],
          "attributes": {
            "src": "designs/779/top.sv:31.18-31.29"
          }
        },
        "input_data": {
          "hide_name": 0,
          "bits": [ 2, 3, 4, 5, 6, 7, 8 ],
          "attributes": {
            "src": "designs/779/top.sv:2.17-2.27"
          }
        },
        "output_data": {
          "hide_name": 0,
          "bits": [ 9, 10, 11, 12, 13, 14, 15, 16, 17 ],
          "attributes": {
            "src": "designs/779/top.sv:3.18-3.29"
          }
        },
        "temp_0": {
          "hide_name": 0,
          "bits": [ 25, 26, 27, 28, 29, 30, 31, 32, 33, 34, 35, 36, 37, 38, 39, 40, 41, 42, 43, 44, 45, 46, 47 ],
          "attributes": {
            "src": "designs/779/top.sv:6.18-6.24"
          }
        },
        "temp_1": {
          "hide_name": 0,
          "bits": [ 124, 125 ],
          "attributes": {
            "src": "designs/779/top.sv:7.17-7.23"
          }
        },
        "temp_10": {
          "hide_name": 0,
          "bits": [ 599, 600, 601, 602, 603, 604, 605, 606, 607 ],
          "attributes": {
          }
        },
        "temp_12": {
          "hide_name": 0,
          "bits": [ 608, 609, 610, 611, 612, 613, 614, 615, 616, 944, 945, 946, 947, 948, 949, 950 ],
          "attributes": {
            "src": "designs/779/top.sv:18.18-18.25",
            "unused_bits": "9 10 11 12 13 14 15"
          }
        },
        "temp_2": {
          "hide_name": 0,
          "bits": [ 244, 245, 246, 247, 248, 249, 250, 251, 252, 253, 254, 255, 256, 257, 258, 259, 260, 261, 262, 263, 264, 265, 266, "0", "0", "0", "0", "0", "0", "0" ],
          "attributes": {
            "src": "designs/779/top.sv:8.18-8.24"
          }
        },
        "temp_3": {
          "hide_name": 0,
          "bits": [ 345, "0", "0", "0", "0", "0", "0", "0", "0", "0", "0", "0", "0", "0", "0", "0" ],
          "attributes": {
            "src": "designs/779/top.sv:9.18-9.24"
          }
        },
        "temp_4": {
          "hide_name": 0,
          "bits": [ 210, 211, 212, 213 ],
          "attributes": {
            "src": "designs/779/top.sv:10.17-10.23"
          }
        },
        "temp_6": {
          "hide_name": 0,
          "bits": [ 646, 647, 648, 649, 650, 651, 652, 653 ],
          "attributes": {
            "src": "designs/779/top.sv:12.17-12.23"
          }
        },
        "temp_7": {
          "hide_name": 0,
          "bits": [ 321, 322, 323, 324, 325, 326, 327, 328, 329, 330, 331, 332, 333, 334, 335, 336, 337, 338, 339, 340, 341, 342, 343, 344 ],
          "attributes": {
            "src": "designs/779/top.sv:13.18-13.24"
          }
        },
        "temp_8": {
          "hide_name": 0,
          "bits": [ 674, "0", "0", "0", "0", "0", "0", "0", "0", "0", "0", "0", "0", "0", "0", "0", "0", "0", "0", "0", "0", "0", "0", "0", "0", "0", "0", "0", "0", "0", "0" ],
          "attributes": {
            "src": "designs/779/top.sv:14.18-14.24"
          }
        },
        "temp_9": {
          "hide_name": 0,
          "bits": [ 746, 747, 748, 749, 750, 751, 752, 590, 591, 592, 593, 594, 595, 596, 597, 598 ],
          "attributes": {
            "src": "designs/779/top.sv:15.18-15.24"
          }
        }
      }
    }
  }
}
