{
  "creator": "Yosys 0.60 (git sha1 5bafeb77dc71e054fa331ab9efa613e6fb0a1c49, clang++ 17.0.0 -fPIC -O3)",
  "modules": {
    "top": {
      "attributes": {
        "top": "00000000000000000000000000000001",
        "src": "designs/1892/top.sv:1.1-48.10"
      },
      "ports": {
        "input_data": {
          "direction": "input",
          "bits": [ 2, 3, 4 ]
        },
        "output_data": {
          "direction": "output",
          "bits": [ 5, 6, 7, 8, 9, 10 ]
        }
      },
      "cells": {
        "$add$designs/1892/top.sv:35$32": {
          "hide_name": 1,
          "type": "$add",
          "parameters": {
            "A_SIGNED": "00000000000000000000000000000000",
            "A_WIDTH": "00000000000000000000000000010100",
            "B_SIGNED": "00000000000000000000000000000000",
            "B_WIDTH": "00000000000000000000000000011010",
            "Y_WIDTH": "00000000000000000000000000011010"
          },
          "attributes": {
            "src": "designs/1892/top.sv:35.43-35.102"
          },
          "port_directions": {
            "A": "input",
            "B": "input",
            "Y": "output"
          },
          "connections": {
            "A": [ 11, 12, 13, 14, 15, 16, 17, 17, 17, 17, 17, 17, 17, 17, 17, 17, 17, 17, 17, 17 ],
            "B": [ 18, 19, 20, 21, 22, 23, 24, 25, 26, 27, 28, 29, 30, 31, 32, 33, 34, 35, 36, 37, 38, 39, 40, 41, 42, 43 ],
            "Y": [ 44, 45, 46, 47, 48, 49, 50, 51, 52, 53, 54, 55, 56, 57, 58, 59, 60, 61, 62, 63, 64, 65, 66, 67, 68, 69 ]
          }
        },
        "$add$designs/1892/top.sv:37$38": {
          "hide_name": 1,
          "type": "$add",
          "parameters": {
            "A_SIGNED": "00000000000000000000000000000000",
            "A_WIDTH": "00000000000000000000000000001011",
            "B_SIGNED": "00000000000000000000000000000000",
            "B_WIDTH": "00000000000000000000000000000011",
            "Y_WIDTH": "00000000000000000000000000001011"
          },
          "attributes": {
            "src": "designs/1892/top.sv:37.55-37.106"
          },
          "port_directions": {
            "A": "input",
            "B": "input",
            "Y": "output"
          },
          "connections": {
            "A": [ 70, 71, 72, 73, 74, 75, 76, 77, 78, 79, 80 ],
            "B": [ 2, 81, 82 ],
            "Y": [ 83, 84, 85, 86, 87, 88, 89, 90, 91, 92, 93 ]
          }
        },
        "$auto$opt_expr.cc:276:group_cell_inputs$101": {
          "hide_name": 1,
          "type": "$or",
          "parameters": {
            "A_SIGNED": "00000000000000000000000000000000",
            "A_WIDTH": "00000000000000000000000000000011",
            "B_SIGNED": "00000000000000000000000000000000",
            "B_WIDTH": "00000000000000000000000000000011",
            "Y_WIDTH": "00000000000000000000000000000011"
          },
          "attributes": {
          },
          "port_directions": {
            "A": "input",
            "B": "input",
            "Y": "output"
          },
          "connections": {
            "A": [ 94, 95, 96 ],
            "B": [ 2, 3, 4 ],
            "Y": [ 97, 98, 99 ]
          }
        },
        "$auto$opt_expr.cc:276:group_cell_inputs$104": {
          "hide_name": 1,
          "type": "$xor",
          "parameters": {
            "A_SIGNED": "00000000000000000000000000000000",
            "A_WIDTH": "00000000000000000000000000000011",
            "B_SIGNED": "00000000000000000000000000000000",
            "B_WIDTH": "00000000000000000000000000000011",
            "Y_WIDTH": "00000000000000000000000000000011"
          },
          "attributes": {
          },
          "port_directions": {
            "A": "input",
            "B": "input",
            "Y": "output"
          },
          "connections": {
            "A": [ 97, 98, 99 ],
            "B": [ 2, 3, 4 ],
            "Y": [ 100, 101, 102 ]
          }
        },
        "$auto$opt_expr.cc:276:group_cell_inputs$107": {
          "hide_name": 1,
          "type": "$xor",
          "parameters": {
            "A_SIGNED": "00000000000000000000000000000000",
            "A_WIDTH": "00000000000000000000000000000011",
            "B_SIGNED": "00000000000000000000000000000000",
            "B_WIDTH": "00000000000000000000000000000011",
            "Y_WIDTH": "00000000000000000000000000000011"
          },
          "attributes": {
          },
          "port_directions": {
            "A": "input",
            "B": "input",
            "Y": "output"
          },
          "connections": {
            "A": [ 103, 104, 105 ],
            "B": [ 2, 3, 4 ],
            "Y": [ 106, 107, 108 ]
          }
        },
        "$auto$opt_expr.cc:276:group_cell_inputs$121": {
          "hide_name": 1,
          "type": "$and",
          "parameters": {
            "A_SIGNED": "00000000000000000000000000000000",
            "A_WIDTH": "00000000000000000000000000000001",
            "B_SIGNED": "00000000000000000000000000000000",
            "B_WIDTH": "00000000000000000000000000000001",
            "Y_WIDTH": "00000000000000000000000000000001"
          },
          "attributes": {
          },
          "port_directions": {
            "A": "input",
            "B": "input",
            "Y": "output"
          },
          "connections": {
            "A": [ 2 ],
            "B": [ 109 ],
            "Y": [ 110 ]
          }
        },
        "$auto$opt_expr.cc:276:group_cell_inputs$125": {
          "hide_name": 1,
          "type": "$or",
          "parameters": {
            "A_SIGNED": "00000000000000000000000000000000",
            "A_WIDTH": "00000000000000000000000000000011",
            "B_SIGNED": "00000000000000000000000000000000",
            "B_WIDTH": "00000000000000000000000000000011",
            "Y_WIDTH": "00000000000000000000000000000011"
          },
          "attributes": {
          },
          "port_directions": {
            "A": "input",
            "B": "input",
            "Y": "output"
          },
          "connections": {
            "A": [ 111, 112, 113 ],
            "B": [ 2, 81, 82 ],
            "Y": [ 114, 115, 116 ]
          }
        },
        "$auto$opt_expr.cc:276:group_cell_inputs$128": {
          "hide_name": 1,
          "type": "$or",
          "parameters": {
            "A_SIGNED": "00000000000000000000000000000000",
            "A_WIDTH": "00000000000000000000000000000011",
            "B_SIGNED": "00000000000000000000000000000000",
            "B_WIDTH": "00000000000000000000000000000011",
            "Y_WIDTH": "00000000000000000000000000000011"
          },
          "attributes": {
          },
          "port_directions": {
            "A": "input",
            "B": "input",
            "Y": "output"
          },
          "connections": {
            "A": [ 2, 3, 4 ],
            "B": [ 117, 118, 119 ],
            "Y": [ 120, 121, 122 ]
          }
        },
        "$auto$opt_expr.cc:276:group_cell_inputs$131": {
          "hide_name": 1,
          "type": "$xor",
          "parameters": {
            "A_SIGNED": "00000000000000000000000000000000",
            "A_WIDTH": "00000000000000000000000000000001",
            "B_SIGNED": "00000000000000000000000000000000",
            "B_WIDTH": "00000000000000000000000000000001",
            "Y_WIDTH": "00000000000000000000000000000001"
          },
          "attributes": {
          },
          "port_directions": {
            "A": "input",
            "B": "input",
            "Y": "output"
          },
          "connections": {
            "A": [ 123 ],
            "B": [ 109 ],
            "Y": [ 124 ]
          }
        },
        "$auto$opt_expr.cc:276:group_cell_inputs$134": {
          "hide_name": 1,
          "type": "$or",
          "parameters": {
            "A_SIGNED": "00000000000000000000000000000000",
            "A_WIDTH": "00000000000000000000000000000011",
            "B_SIGNED": "00000000000000000000000000000000",
            "B_WIDTH": "00000000000000000000000000000011",
            "Y_WIDTH": "00000000000000000000000000000011"
          },
          "attributes": {
          },
          "port_directions": {
            "A": "input",
            "B": "input",
            "Y": "output"
          },
          "connections": {
            "A": [ 125, 126, 127 ],
            "B": [ 2, 3, 4 ],
            "Y": [ 128, 129, 130 ]
          }
        },
        "$auto$opt_expr.cc:276:group_cell_inputs$137": {
          "hide_name": 1,
          "type": "$and",
          "parameters": {
            "A_SIGNED": "00000000000000000000000000000000",
            "A_WIDTH": "00000000000000000000000000000011",
            "B_SIGNED": "00000000000000000000000000000000",
            "B_WIDTH": "00000000000000000000000000000011",
            "Y_WIDTH": "00000000000000000000000000000011"
          },
          "attributes": {
          },
          "port_directions": {
            "A": "input",
            "B": "input",
            "Y": "output"
          },
          "connections": {
            "A": [ 128, 129, 130 ],
            "B": [ 2, 3, 4 ],
            "Y": [ 131, 132, 133 ]
          }
        },
        "$auto$opt_expr.cc:276:group_cell_inputs$141": {
          "hide_name": 1,
          "type": "$not",
          "parameters": {
            "A_SIGNED": "00000000000000000000000000000000",
            "A_WIDTH": "00000000000000000000000000001010",
            "Y_WIDTH": "00000000000000000000000000001010"
          },
          "attributes": {
          },
          "port_directions": {
            "A": "input",
            "Y": "output"
          },
          "connections": {
            "A": [ 114, 115, 116, 134, 135, 136, 137, 138, 139, 140 ],
            "Y": [ 141, 142, 143, 144, 145, 146, 147, 148, 149, 150 ]
          }
        },
        "$auto$opt_expr.cc:276:group_cell_inputs$145": {
          "hide_name": 1,
          "type": "$xor",
          "parameters": {
            "A_SIGNED": "00000000000000000000000000000000",
            "A_WIDTH": "00000000000000000000000000000001",
            "B_SIGNED": "00000000000000000000000000000000",
            "B_WIDTH": "00000000000000000000000000000001",
            "Y_WIDTH": "00000000000000000000000000000001"
          },
          "attributes": {
          },
          "port_directions": {
            "A": "input",
            "B": "input",
            "Y": "output"
          },
          "connections": {
            "A": [ 83 ],
            "B": [ 109 ],
            "Y": [ 151 ]
          }
        },
        "$auto$opt_expr.cc:276:group_cell_inputs$148": {
          "hide_name": 1,
          "type": "$xor",
          "parameters": {
            "A_SIGNED": "00000000000000000000000000000000",
            "A_WIDTH": "00000000000000000000000000000111",
            "B_SIGNED": "00000000000000000000000000000000",
            "B_WIDTH": "00000000000000000000000000000111",
            "Y_WIDTH": "00000000000000000000000000000111"
          },
          "attributes": {
          },
          "port_directions": {
            "A": "input",
            "B": "input",
            "Y": "output"
          },
          "connections": {
            "A": [ 151, 84, 85, 86, 87, 88, 89 ],
            "B": [ 152, 153, 154, 155, 156, 157, 158 ],
            "Y": [ 159, 160, 161, 162, 163, 164, 165 ]
          }
        },
        "$auto$opt_expr.cc:276:group_cell_inputs$151": {
          "hide_name": 1,
          "type": "$xor",
          "parameters": {
            "A_SIGNED": "00000000000000000000000000000000",
            "A_WIDTH": "00000000000000000000000000000011",
            "B_SIGNED": "00000000000000000000000000000000",
            "B_WIDTH": "00000000000000000000000000000011",
            "Y_WIDTH": "00000000000000000000000000000011"
          },
          "attributes": {
          },
          "port_directions": {
            "A": "input",
            "B": "input",
            "Y": "output"
          },
          "connections": {
            "A": [ 166, 167, 168 ],
            "B": [ 2, 3, 4 ],
            "Y": [ 169, 170, 171 ]
          }
        },
        "$auto$opt_expr.cc:276:group_cell_inputs$154": {
          "hide_name": 1,
          "type": "$xor",
          "parameters": {
            "A_SIGNED": "00000000000000000000000000000000",
            "A_WIDTH": "00000000000000000000000000000011",
            "B_SIGNED": "00000000000000000000000000000000",
            "B_WIDTH": "00000000000000000000000000000011",
            "Y_WIDTH": "00000000000000000000000000000011"
          },
          "attributes": {
          },
          "port_directions": {
            "A": "input",
            "B": "input",
            "Y": "output"
          },
          "connections": {
            "A": [ 172, 173, 174 ],
            "B": [ 2, 81, 82 ],
            "Y": [ 175, 176, 177 ]
          }
        },
        "$auto$opt_expr.cc:276:group_cell_inputs$200": {
          "hide_name": 1,
          "type": "$not",
          "parameters": {
            "A_SIGNED": "00000000000000000000000000000000",
            "A_WIDTH": "00000000000000000000000000000010",
            "Y_WIDTH": "00000000000000000000000000000010"
          },
          "attributes": {
          },
          "port_directions": {
            "A": "input",
            "Y": "output"
          },
          "connections": {
            "A": [ 81, 82 ],
            "Y": [ 178, 179 ]
          }
        },
        "$auto$opt_expr.cc:276:group_cell_inputs$93": {
          "hide_name": 1,
          "type": "$and",
          "parameters": {
            "A_SIGNED": "00000000000000000000000000000000",
            "A_WIDTH": "00000000000000000000000000000010",
            "B_SIGNED": "00000000000000000000000000000000",
            "B_WIDTH": "00000000000000000000000000000010",
            "Y_WIDTH": "00000000000000000000000000000010"
          },
          "attributes": {
          },
          "port_directions": {
            "A": "input",
            "B": "input",
            "Y": "output"
          },
          "connections": {
            "A": [ 3, 4 ],
            "B": [ 3, 4 ],
            "Y": [ 81, 82 ]
          }
        },
        "$auto$opt_expr.cc:276:group_cell_inputs$98": {
          "hide_name": 1,
          "type": "$or",
          "parameters": {
            "A_SIGNED": "00000000000000000000000000000000",
            "A_WIDTH": "00000000000000000000000000000011",
            "B_SIGNED": "00000000000000000000000000000000",
            "B_WIDTH": "00000000000000000000000000000011",
            "Y_WIDTH": "00000000000000000000000000000011"
          },
          "attributes": {
          },
          "port_directions": {
            "A": "input",
            "B": "input",
            "Y": "output"
          },
          "connections": {
            "A": [ 2, 81, 82 ],
            "B": [ 2, 3, 4 ],
            "Y": [ 94, 95, 96 ]
          }
        },
        "$eq$designs/1892/top.sv:36$35": {
          "hide_name": 1,
          "type": "$eq",
          "parameters": {
            "A_SIGNED": "00000000000000000000000000000000",
            "A_WIDTH": "00000000000000000000000000011010",
            "B_SIGNED": "00000000000000000000000000000000",
            "B_WIDTH": "00000000000000000000000000011010",
            "Y_WIDTH": "00000000000000000000000000000001"
          },
          "attributes": {
            "src": "designs/1892/top.sv:36.31-36.80"
          },
          "port_directions": {
            "A": "input",
            "B": "input",
            "Y": "output"
          },
          "connections": {
            "A": [ 131, 132, 133, "0", "0", "0", "0", "0", "0", "0", "0", "0", "0", "0", "0", "0", "0", "0", "0", "0", "0", "0", "0", "0", "0", "0" ],
            "B": [ 180, 181, 182, 183, 184, 185, 186, 187, 188, 189, 190, 191, 192, 193, 194, 195, 196, 197, 198, 199, 200, 201, 202, 203, 204, 205 ],
            "Y": [ 206 ]
          }
        },
        "$gt$designs/1892/top.sv:30$13": {
          "hide_name": 1,
          "type": "$gt",
          "parameters": {
            "A_SIGNED": "00000000000000000000000000000000",
            "A_WIDTH": "00000000000000000000000000000011",
            "B_SIGNED": "00000000000000000000000000000000",
            "B_WIDTH": "00000000000000000000000000000110",
            "Y_WIDTH": "00000000000000000000000000000001"
          },
          "attributes": {
            "src": "designs/1892/top.sv:30.22-30.52"
          },
          "port_directions": {
            "A": "input",
            "B": "input",
            "Y": "output"
          },
          "connections": {
            "A": [ 2, 3, 4 ],
            "B": [ 117, 118, 119, 207, 208, 209 ],
            "Y": [ 109 ]
          }
        },
        "$mul$designs/1892/top.sv:27$6": {
          "hide_name": 1,
          "type": "$mul",
          "parameters": {
            "A_SIGNED": "00000000000000000000000000000000",
            "A_WIDTH": "00000000000000000000000000000101",
            "B_SIGNED": "00000000000000000000000000000000",
            "B_WIDTH": "00000000000000000000000000000011",
            "Y_WIDTH": "00000000000000000000000000000110"
          },
          "attributes": {
            "src": "designs/1892/top.sv:27.42-27.124"
          },
          "port_directions": {
            "A": "input",
            "B": "input",
            "Y": "output"
          },
          "connections": {
            "A": [ 100, 101, 102, "0", "0" ],
            "B": [ 2, 3, 4 ],
            "Y": [ 103, 104, 105, 210, 211, 212 ]
          }
        },
        "$mul$designs/1892/top.sv:28$10": {
          "hide_name": 1,
          "type": "$mul",
          "parameters": {
            "A_SIGNED": "00000000000000000000000000000000",
            "A_WIDTH": "00000000000000000000000000000011",
            "B_SIGNED": "00000000000000000000000000000000",
            "B_WIDTH": "00000000000000000000000000000101",
            "Y_WIDTH": "00000000000000000000000000000101"
          },
          "attributes": {
            "src": "designs/1892/top.sv:28.44-28.82"
          },
          "port_directions": {
            "A": "input",
            "B": "input",
            "Y": "output"
          },
          "connections": {
            "A": [ 2, 3, 4 ],
            "B": [ 178, 179, "1", "1", "1" ],
            "Y": [ 213, 214, 215, 216, 217 ]
          }
        },
        "$mul$designs/1892/top.sv:28$11": {
          "hide_name": 1,
          "type": "$mul",
          "parameters": {
            "A_SIGNED": "00000000000000000000000000000000",
            "A_WIDTH": "00000000000000000000000000000101",
            "B_SIGNED": "00000000000000000000000000000000",
            "B_WIDTH": "00000000000000000000000000000101",
            "Y_WIDTH": "00000000000000000000000000000110"
          },
          "attributes": {
            "src": "designs/1892/top.sv:28.33-28.93"
          },
          "port_directions": {
            "A": "input",
            "B": "input",
            "Y": "output"
          },
          "connections": {
            "A": [ 213, 214, 215, 216, 217 ],
            "B": [ 2, 81, 82, "0", "0" ],
            "Y": [ 218, 219, 220, 221, 222, 223 ]
          }
        },
        "$mul$designs/1892/top.sv:33$21": {
          "hide_name": 1,
          "type": "$mul",
          "parameters": {
            "A_SIGNED": "00000000000000000000000000000000",
            "A_WIDTH": "00000000000000000000000000000101",
            "B_SIGNED": "00000000000000000000000000000000",
            "B_WIDTH": "00000000000000000000000000000101",
            "Y_WIDTH": "00000000000000000000000000001010"
          },
          "attributes": {
            "src": "designs/1892/top.sv:33.33-33.112"
          },
          "port_directions": {
            "A": "input",
            "B": "input",
            "Y": "output"
          },
          "connections": {
            "A": [ 110, "0", "0", "0", "0" ],
            "B": [ 2, 81, 82, "0", "0" ],
            "Y": [ 111, 112, 113, 134, 135, 136, 137, 138, 139, 140 ]
          }
        },
        "$mul$designs/1892/top.sv:34$27": {
          "hide_name": 1,
          "type": "$mul",
          "parameters": {
            "A_SIGNED": "00000000000000000000000000000000",
            "A_WIDTH": "00000000000000000000000000011000",
            "B_SIGNED": "00000000000000000000000000000000",
            "B_WIDTH": "00000000000000000000000000001011",
            "Y_WIDTH": "00000000000000000000000000011100"
          },
          "attributes": {
            "src": "designs/1892/top.sv:34.23-34.128"
          },
          "port_directions": {
            "A": "input",
            "B": "input",
            "Y": "output"
          },
          "connections": {
            "A": [ 224, 225, 226, 227, 228, 229, 230, 231, 232, 233, 234, 235, 236, 237, 238, 239, 240, 241, 242, 243, 244, 245, 246, 247 ],
            "B": [ 248, 249, 250, 251, 252, 253, 254, 254, 254, 254, 254 ],
            "Y": [ 125, 126, 127, 255, 256, 257, 258, 259, 260, 261, 262, 263, 264, 265, 266, 267, 268, 269, 270, 271, 272, 152, 153, 154, 155, 156, 157, 158 ]
          }
        },
        "$mul$designs/1892/top.sv:35$29": {
          "hide_name": 1,
          "type": "$mul",
          "parameters": {
            "A_SIGNED": "00000000000000000000000000000000",
            "A_WIDTH": "00000000000000000000000000000011",
            "B_SIGNED": "00000000000000000000000000000000",
            "B_WIDTH": "00000000000000000000000000000011",
            "Y_WIDTH": "00000000000000000000000000000110"
          },
          "attributes": {
            "src": "designs/1892/top.sv:35.55-35.78"
          },
          "port_directions": {
            "A": "input",
            "B": "input",
            "Y": "output"
          },
          "connections": {
            "A": [ 2, 3, 4 ],
            "B": [ 2, 3, 4 ],
            "Y": [ 273, 274, 275, 276, 277, 278 ]
          }
        },
        "$mul$designs/1892/top.sv:37$42": {
          "hide_name": 1,
          "type": "$mul",
          "parameters": {
            "A_SIGNED": "00000000000000000000000000000000",
            "A_WIDTH": "00000000000000000000000000011101",
            "B_SIGNED": "00000000000000000000000000000000",
            "B_WIDTH": "00000000000000000000000000000110",
            "Y_WIDTH": "00000000000000000000000000011101"
          },
          "attributes": {
            "src": "designs/1892/top.sv:37.23-37.174"
          },
          "port_directions": {
            "A": "input",
            "B": "input",
            "Y": "output"
          },
          "connections": {
            "A": [ 279, 280, 281, 282, 283, 284, 285, 286, 287, 288, 289, 290, 290, 290, 290, 290, 290, 290, 290, 290, 290, 290, 290, 290, 290, 290, 290, 290, 290 ],
            "B": [ 117, 118, 119, 207, 208, 209 ],
            "Y": [ 291, 292, 293, 294, 295, 296, 297, 298, 299, 300, 301, 302, 303, 304, 305, 306, 307, 308, 309, 310, 311, 312, 313, 314, 315, 316, 317, 318, 319 ]
          }
        },
        "$mul$designs/1892/top.sv:38$45": {
          "hide_name": 1,
          "type": "$mul",
          "parameters": {
            "A_SIGNED": "00000000000000000000000000000000",
            "A_WIDTH": "00000000000000000000000000001011",
            "B_SIGNED": "00000000000000000000000000000000",
            "B_WIDTH": "00000000000000000000000000011101",
            "Y_WIDTH": "00000000000000000000000000011101"
          },
          "attributes": {
            "src": "designs/1892/top.sv:38.73-38.152"
          },
          "port_directions": {
            "A": "input",
            "B": "input",
            "Y": "output"
          },
          "connections": {
            "A": [ 320, 321, 322, 323, 324, 325, 326, 327, 327, 327, 327 ],
            "B": [ 291, 292, 293, 294, 295, 296, 297, 298, 299, 300, 301, 302, 303, 304, 305, 306, 307, 308, 309, 310, 311, 312, 313, 314, 315, 316, 317, 318, 319 ],
            "Y": [ 166, 167, 168, 328, 329, 330, 331, 332, 333, 334, 335, 336, 337, 338, 339, 340, 341, 342, 343, 344, 345, 346, 347, 348, 349, 350, 351, 352, 353 ]
          }
        },
        "$mul$designs/1892/top.sv:38$47": {
          "hide_name": 1,
          "type": "$mul",
          "parameters": {
            "A_SIGNED": "00000000000000000000000000000000",
            "A_WIDTH": "00000000000000000000000000011101",
            "B_SIGNED": "00000000000000000000000000000000",
            "B_WIDTH": "00000000000000000000000000001011",
            "Y_WIDTH": "00000000000000000000000000011101"
          },
          "attributes": {
            "src": "designs/1892/top.sv:38.53-38.178"
          },
          "port_directions": {
            "A": "input",
            "B": "input",
            "Y": "output"
          },
          "connections": {
            "A": [ 169, 170, 171, 328, 329, 330, 331, 332, 333, 334, 335, 336, 337, 338, 339, 340, 341, 342, 343, 344, 345, 346, 347, 348, 349, 350, 351, 352, 353 ],
            "B": [ 248, 249, 250, 251, 252, 253, 254, 254, 254, 254, 254 ],
            "Y": [ 354, 355, 356, 357, 358, 359, 360, 361, 362, 363, 364, 365, 366, 367, 368, 369, 370, 371, 372, 373, 374, 375, 376, 377, 378, 379, 380, 381, 382 ]
          }
        },
        "$mul$designs/1892/top.sv:38$48": {
          "hide_name": 1,
          "type": "$mul",
          "parameters": {
            "A_SIGNED": "00000000000000000000000000000000",
            "A_WIDTH": "00000000000000000000000000011101",
            "B_SIGNED": "00000000000000000000000000000000",
            "B_WIDTH": "00000000000000000000000000000011",
            "Y_WIDTH": "00000000000000000000000000010010"
          },
          "attributes": {
            "src": "designs/1892/top.sv:38.44-38.193"
          },
          "port_directions": {
            "A": "input",
            "B": "input",
            "Y": "output"
          },
          "connections": {
            "A": [ 354, 355, 356, 357, 358, 359, 360, 361, 362, 363, 364, 365, 366, 367, 368, 369, 370, 371, 372, 373, 374, 375, 376, 377, 378, 379, 380, 381, 382 ],
            "B": [ 2, 3, 4 ],
            "Y": [ 172, 173, 174, 383, 384, 385, 386, 387, 388, 389, 390, 391, 392, 393, 394, 395, 396, 397 ]
          }
        },
        "$not$designs/1892/top.sv:35$31": {
          "hide_name": 1,
          "type": "$not",
          "parameters": {
            "A_SIGNED": "00000000000000000000000000000000",
            "A_WIDTH": "00000000000000000000000000011010",
            "Y_WIDTH": "00000000000000000000000000011010"
          },
          "attributes": {
            "src": "designs/1892/top.sv:35.94-35.101"
          },
          "port_directions": {
            "A": "input",
            "Y": "output"
          },
          "connections": {
            "A": [ 128, 129, 130, 255, 256, 257, 258, 259, 260, 261, 262, 263, 264, 265, 266, 267, 268, 269, 270, 271, 272, 152, 153, 154, 155, 156 ],
            "Y": [ 18, 19, 20, 21, 22, 23, 24, 25, 26, 27, 28, 29, 30, 31, 32, 33, 34, 35, 36, 37, 38, 39, 40, 41, 42, 43 ]
          }
        },
        "$or$designs/1892/top.sv:46$87": {
          "hide_name": 1,
          "type": "$or",
          "parameters": {
            "A_SIGNED": "00000000000000000000000000000000",
            "A_WIDTH": "00000000000000000000000000000110",
            "B_SIGNED": "00000000000000000000000000000000",
            "B_WIDTH": "00000000000000000000000000000110",
            "Y_WIDTH": "00000000000000000000000000000110"
          },
          "attributes": {
            "src": "designs/1892/top.sv:46.37-46.67"
          },
          "port_directions": {
            "A": "input",
            "B": "input",
            "Y": "output"
          },
          "connections": {
            "A": [ 114, 115, 116, 134, 135, 136 ],
            "B": [ 175, 176, 177, 383, 384, 385 ],
            "Y": [ 5, 6, 7, 8, 9, 10 ]
          }
        },
        "$sub$designs/1892/top.sv:27$8": {
          "hide_name": 1,
          "type": "$sub",
          "parameters": {
            "A_SIGNED": "00000000000000000000000000000000",
            "A_WIDTH": "00000000000000000000000000000110",
            "B_SIGNED": "00000000000000000000000000000000",
            "B_WIDTH": "00000000000000000000000000000011",
            "Y_WIDTH": "00000000000000000000000000000110"
          },
          "attributes": {
            "src": "designs/1892/top.sv:27.32-27.153"
          },
          "port_directions": {
            "A": "input",
            "B": "input",
            "Y": "output"
          },
          "connections": {
            "A": [ 106, 107, 108, 210, 211, 212 ],
            "B": [ 2, 3, 4 ],
            "Y": [ 117, 118, 119, 207, 208, 209 ]
          }
        },
        "$sub$designs/1892/top.sv:28$12": {
          "hide_name": 1,
          "type": "$sub",
          "parameters": {
            "A_SIGNED": "00000000000000000000000000000000",
            "A_WIDTH": "00000000000000000000000000000110",
            "B_SIGNED": "00000000000000000000000000000000",
            "B_WIDTH": "00000000000000000000000000000101",
            "Y_WIDTH": "00000000000000000000000000000111"
          },
          "attributes": {
            "src": "designs/1892/top.sv:28.22-28.109"
          },
          "port_directions": {
            "A": "input",
            "B": "input",
            "Y": "output"
          },
          "connections": {
            "A": [ 218, 219, 220, 221, 222, 223 ],
            "B": [ 2, 81, 82, "0", "0" ],
            "Y": [ 248, 249, 250, 251, 252, 253, 254 ]
          }
        },
        "$sub$designs/1892/top.sv:34$24": {
          "hide_name": 1,
          "type": "$sub",
          "parameters": {
            "A_SIGNED": "00000000000000000000000000000000",
            "A_WIDTH": "00000000000000000000000000000110",
            "B_SIGNED": "00000000000000000000000000000000",
            "B_WIDTH": "00000000000000000000000000000011",
            "Y_WIDTH": "00000000000000000000000000000111"
          },
          "attributes": {
            "src": "designs/1892/top.sv:34.46-34.90"
          },
          "port_directions": {
            "A": "input",
            "B": "input",
            "Y": "output"
          },
          "connections": {
            "A": [ 120, 121, 122, 207, 208, 209 ],
            "B": [ 2, 3, 4 ],
            "Y": [ 123, 398, 399, 400, 401, 402, 403 ]
          }
        },
        "$sub$designs/1892/top.sv:34$26": {
          "hide_name": 1,
          "type": "$sub",
          "parameters": {
            "A_SIGNED": "00000000000000000000000000000000",
            "A_WIDTH": "00000000000000000000000000011000",
            "B_SIGNED": "00000000000000000000000000000000",
            "B_WIDTH": "00000000000000000000000000000110",
            "Y_WIDTH": "00000000000000000000000000011000"
          },
          "attributes": {
            "src": "designs/1892/top.sv:34.34-34.117"
          },
          "port_directions": {
            "A": "input",
            "B": "input",
            "Y": "output"
          },
          "connections": {
            "A": [ 124, 398, 399, 400, 401, 402, 403, 403, 403, 403, 403, 403, 403, 403, 403, 403, 403, 403, 403, 403, 403, 403, 403, 403 ],
            "B": [ 117, 118, 119, 207, 208, 209 ],
            "Y": [ 224, 225, 226, 227, 228, 229, 230, 231, 232, 233, 234, 235, 236, 237, 238, 239, 240, 241, 242, 243, 244, 245, 246, 247 ]
          }
        },
        "$sub$designs/1892/top.sv:35$30": {
          "hide_name": 1,
          "type": "$sub",
          "parameters": {
            "A_SIGNED": "00000000000000000000000000000000",
            "A_WIDTH": "00000000000000000000000000000110",
            "B_SIGNED": "00000000000000000000000000000000",
            "B_WIDTH": "00000000000000000000000000000011",
            "Y_WIDTH": "00000000000000000000000000000111"
          },
          "attributes": {
            "src": "designs/1892/top.sv:35.54-35.88"
          },
          "port_directions": {
            "A": "input",
            "B": "input",
            "Y": "output"
          },
          "connections": {
            "A": [ 273, 274, 275, 276, 277, 278 ],
            "B": [ 2, 3, 4 ],
            "Y": [ 11, 12, 13, 14, 15, 16, 17 ]
          }
        },
        "$sub$designs/1892/top.sv:35$33": {
          "hide_name": 1,
          "type": "$sub",
          "parameters": {
            "A_SIGNED": "00000000000000000000000000000000",
            "A_WIDTH": "00000000000000000000000000011010",
            "B_SIGNED": "00000000000000000000000000000000",
            "B_WIDTH": "00000000000000000000000000000011",
            "Y_WIDTH": "00000000000000000000000000011010"
          },
          "attributes": {
            "src": "designs/1892/top.sv:35.32-35.113"
          },
          "port_directions": {
            "A": "input",
            "B": "input",
            "Y": "output"
          },
          "connections": {
            "A": [ 44, 45, 46, 47, 48, 49, 50, 51, 52, 53, 54, 55, 56, 57, 58, 59, 60, 61, 62, 63, 64, 65, 66, 67, 68, 69 ],
            "B": [ 2, 81, 82 ],
            "Y": [ 180, 181, 182, 183, 184, 185, 186, 187, 188, 189, 190, 191, 192, 193, 194, 195, 196, 197, 198, 199, 200, 201, 202, 203, 204, 205 ]
          }
        },
        "$sub$designs/1892/top.sv:37$37": {
          "hide_name": 1,
          "type": "$sub",
          "parameters": {
            "A_SIGNED": "00000000000000000000000000000000",
            "A_WIDTH": "00000000000000000000000000000011",
            "B_SIGNED": "00000000000000000000000000000000",
            "B_WIDTH": "00000000000000000000000000001011",
            "Y_WIDTH": "00000000000000000000000000001011"
          },
          "attributes": {
            "src": "designs/1892/top.sv:37.64-37.95"
          },
          "port_directions": {
            "A": "input",
            "B": "input",
            "Y": "output"
          },
          "connections": {
            "A": [ 2, 3, 4 ],
            "B": [ 141, 142, 143, 144, 145, 146, 147, 148, 149, 150, "1" ],
            "Y": [ 70, 71, 72, 73, 74, 75, 76, 77, 78, 79, 80 ]
          }
        },
        "$sub$designs/1892/top.sv:37$41": {
          "hide_name": 1,
          "type": "$sub",
          "parameters": {
            "A_SIGNED": "00000000000000000000000000000000",
            "A_WIDTH": "00000000000000000000000000001011",
            "B_SIGNED": "00000000000000000000000000000000",
            "B_WIDTH": "00000000000000000000000000000011",
            "Y_WIDTH": "00000000000000000000000000001100"
          },
          "attributes": {
            "src": "designs/1892/top.sv:37.24-37.158"
          },
          "port_directions": {
            "A": "input",
            "B": "input",
            "Y": "output"
          },
          "connections": {
            "A": [ 159, 160, 161, 162, 163, 164, 165, 90, 91, 92, 93 ],
            "B": [ 206, 206, 206 ],
            "Y": [ 279, 280, 281, 282, 283, 284, 285, 286, 287, 288, 289, 290 ]
          }
        },
        "$sub$designs/1892/top.sv:38$44": {
          "hide_name": 1,
          "type": "$sub",
          "parameters": {
            "A_SIGNED": "00000000000000000000000000000001",
            "A_WIDTH": "00000000000000000000000000000100",
            "B_SIGNED": "00000000000000000000000000000001",
            "B_WIDTH": "00000000000000000000000000000111",
            "Y_WIDTH": "00000000000000000000000000001000"
          },
          "attributes": {
            "src": "designs/1892/top.sv:38.84-38.140"
          },
          "port_directions": {
            "A": "input",
            "B": "input",
            "Y": "output"
          },
          "connections": {
            "A": [ 2, 3, 4, "0" ],
            "B": [ 248, 249, 250, 251, 252, 253, 254 ],
            "Y": [ 320, 321, 322, 323, 324, 325, 326, 327 ]
          }
        }
      },
      "netnames": {
        "$add$designs/1892/top.sv:35$32_Y": {
          "hide_name": 1,
          "bits": [ 44, 45, 46, 47, 48, 49, 50, 51, 52, 53, 54, 55, 56, 57, 58, 59, 60, 61, 62, 63, 64, 65, 66, 67, 68, 69, 404, 405 ],
          "attributes": {
            "src": "designs/1892/top.sv:35.43-35.102",
            "unused_bits": "26 27"
          }
        },
        "$add$designs/1892/top.sv:37$38_Y": {
          "hide_name": 1,
          "bits": [ 83, 84, 85, 86, 87, 88, 89, 90, 91, 92, 93 ],
          "attributes": {
            "src": "designs/1892/top.sv:37.55-37.106"
          }
        },
        "$and$designs/1892/top.sv:33$20_Y": {
          "hide_name": 1,
          "bits": [ 110, "0", "0", "0", "0", "0", "0", "0", "0", "0", "0", "0", "0", "0", "0", "0", "0" ],
          "attributes": {
            "src": "designs/1892/top.sv:33.42-33.101"
          }
        },
        "$and$designs/1892/top.sv:36$34_Y": {
          "hide_name": 1,
          "bits": [ 131, 132, 133, "0", "0", "0", "0", "0", "0", "0", "0", "0", "0", "0", "0", "0", "0", "0", "0", "0", "0", "0", "0", "0", "0", "0", "0", "0" ],
          "attributes": {
            "src": "designs/1892/top.sv:36.40-36.68"
          }
        },
        "$auto$opt_expr.cc:205:group_cell_inputs$100": {
          "hide_name": 1,
          "bits": [ 97, 98, 99 ],
          "attributes": {
          }
        },
        "$auto$opt_expr.cc:205:group_cell_inputs$103": {
          "hide_name": 1,
          "bits": [ 100, 101, 102 ],
          "attributes": {
          }
        },
        "$auto$opt_expr.cc:205:group_cell_inputs$106": {
          "hide_name": 1,
          "bits": [ 106, 107, 108 ],
          "attributes": {
          }
        },
        "$auto$opt_expr.cc:205:group_cell_inputs$108": {
          "hide_name": 1,
          "bits": [ 210, 211, 212 ],
          "attributes": {
          }
        },
        "$auto$opt_expr.cc:205:group_cell_inputs$109": {
          "hide_name": 1,
          "bits": [ 178, 179, "1", "1" ],
          "attributes": {
          }
        },
        "$auto$opt_expr.cc:205:group_cell_inputs$127": {
          "hide_name": 1,
          "bits": [ 120, 121, 122 ],
          "attributes": {
          }
        },
        "$auto$opt_expr.cc:205:group_cell_inputs$130": {
          "hide_name": 1,
          "bits": [ 124 ],
          "attributes": {
          }
        },
        "$auto$opt_expr.cc:205:group_cell_inputs$132": {
          "hide_name": 1,
          "bits": [ 398, 399, 400, 401, 402, 403 ],
          "attributes": {
          }
        },
        "$auto$opt_expr.cc:205:group_cell_inputs$140": {
          "hide_name": 1,
          "bits": [ 141, 142, 143, 144, 145, 146, 147, 148, 149, 150 ],
          "attributes": {
          }
        },
        "$auto$opt_expr.cc:205:group_cell_inputs$144": {
          "hide_name": 1,
          "bits": [ 151 ],
          "attributes": {
          }
        },
        "$auto$opt_expr.cc:205:group_cell_inputs$147": {
          "hide_name": 1,
          "bits": [ 159, 160, 161, 162, 163, 164, 165 ],
          "attributes": {
          }
        },
        "$auto$opt_expr.cc:205:group_cell_inputs$150": {
          "hide_name": 1,
          "bits": [ 169, 170, 171 ],
          "attributes": {
          }
        },
        "$auto$opt_expr.cc:205:group_cell_inputs$152": {
          "hide_name": 1,
          "bits": [ 328, 329, 330, 331, 332, 333, 334, 335, 336, 337, 338, 339, 340, 341, 342, 343, 344, 345, 346, 347, 348, 349, 350, 351, 352, 353 ],
          "attributes": {
          }
        },
        "$auto$opt_expr.cc:205:group_cell_inputs$97": {
          "hide_name": 1,
          "bits": [ 94, 95, 96 ],
          "attributes": {
          }
        },
        "$mul$designs/1892/top.sv:27$6_Y": {
          "hide_name": 1,
          "bits": [ 103, 104, 105, 210, 211, 212 ],
          "attributes": {
            "src": "designs/1892/top.sv:27.42-27.124"
          }
        },
        "$mul$designs/1892/top.sv:28$10_Y": {
          "hide_name": 1,
          "bits": [ 213, 214, 215, 216, 217 ],
          "attributes": {
            "src": "designs/1892/top.sv:28.44-28.82"
          }
        },
        "$mul$designs/1892/top.sv:28$11_Y": {
          "hide_name": 1,
          "bits": [ 218, 219, 220, 221, 222, 223 ],
          "attributes": {
            "src": "designs/1892/top.sv:28.33-28.93"
          }
        },
        "$mul$designs/1892/top.sv:33$21_Y": {
          "hide_name": 1,
          "bits": [ 111, 112, 113, 134, 135, 136, 137, 138, 139, 140, "0", "0", "0", "0", "0", "0", "0" ],
          "attributes": {
            "src": "designs/1892/top.sv:33.33-33.112"
          }
        },
        "$mul$designs/1892/top.sv:34$27_Y": {
          "hide_name": 1,
          "bits": [ 125, 126, 127, 255, 256, 257, 258, 259, 260, 261, 262, 263, 264, 265, 266, 267, 268, 269, 270, 271, 272, 152, 153, 154, 155, 156, 157, 158 ],
          "attributes": {
            "src": "designs/1892/top.sv:34.23-34.128"
          }
        },
        "$mul$designs/1892/top.sv:35$29_Y": {
          "hide_name": 1,
          "bits": [ 273, 274, 275, 276, 277, 278, "0", "0", "0", "0", "0", "0", "0", "0", "0", "0", "0", "0", "0", "0" ],
          "attributes": {
            "src": "designs/1892/top.sv:35.55-35.78"
          }
        },
        "$mul$designs/1892/top.sv:38$45_Y": {
          "hide_name": 1,
          "bits": [ 166, 167, 168, 328, 329, 330, 331, 332, 333, 334, 335, 336, 337, 338, 339, 340, 341, 342, 343, 344, 345, 346, 347, 348, 349, 350, 351, 352, 353 ],
          "attributes": {
            "src": "designs/1892/top.sv:38.73-38.152"
          }
        },
        "$mul$designs/1892/top.sv:38$47_Y": {
          "hide_name": 1,
          "bits": [ 354, 355, 356, 357, 358, 359, 360, 361, 362, 363, 364, 365, 366, 367, 368, 369, 370, 371, 372, 373, 374, 375, 376, 377, 378, 379, 380, 381, 382 ],
          "attributes": {
            "src": "designs/1892/top.sv:38.53-38.178"
          }
        },
        "$mul$designs/1892/top.sv:38$48_Y": {
          "hide_name": 1,
          "bits": [ 172, 173, 174, 383, 384, 385, 386, 387, 388, 389, 390, 391, 392, 393, 394, 395, 396, 397, 406, 407, 408, 409, 410, 411, 412, 413, 414, 415, 416 ],
          "attributes": {
            "src": "designs/1892/top.sv:38.44-38.193",
            "unused_bits": "6 7 8 9 10 11 12 13 14 15 16 17 18 19 20 21 22 23 24 25 26 27 28"
          }
        },
        "$not$designs/1892/top.sv:35$31_Y": {
          "hide_name": 1,
          "bits": [ 18, 19, 20, 21, 22, 23, 24, 25, 26, 27, 28, 29, 30, 31, 32, 33, 34, 35, 36, 37, 38, 39, 40, 41, 42, 43, 417, 418 ],
          "attributes": {
            "src": "designs/1892/top.sv:35.94-35.101",
            "unused_bits": "26 27"
          }
        },
        "$sub$designs/1892/top.sv:34$24_Y": {
          "hide_name": 1,
          "bits": [ 123, 398, 399, 400, 401, 402, 403, 403, 403, 403, 403, 403, 403, 403, 403, 403, 403, 403, 403, 403, 403, 403, 403, 403 ],
          "attributes": {
            "src": "designs/1892/top.sv:34.46-34.90"
          }
        },
        "$sub$designs/1892/top.sv:34$26_Y": {
          "hide_name": 1,
          "bits": [ 224, 225, 226, 227, 228, 229, 230, 231, 232, 233, 234, 235, 236, 237, 238, 239, 240, 241, 242, 243, 244, 245, 246, 247 ],
          "attributes": {
            "src": "designs/1892/top.sv:34.34-34.117"
          }
        },
        "$sub$designs/1892/top.sv:35$30_Y": {
          "hide_name": 1,
          "bits": [ 11, 12, 13, 14, 15, 16, 17, 17, 17, 17, 17, 17, 17, 17, 17, 17, 17, 17, 17, 17 ],
          "attributes": {
            "src": "designs/1892/top.sv:35.54-35.88"
          }
        },
        "$sub$designs/1892/top.sv:37$37_Y": {
          "hide_name": 1,
          "bits": [ 70, 71, 72, 73, 74, 75, 76, 77, 78, 79, 80 ],
          "attributes": {
            "src": "designs/1892/top.sv:37.64-37.95"
          }
        },
        "$sub$designs/1892/top.sv:37$41_Y": {
          "hide_name": 1,
          "bits": [ 279, 280, 281, 282, 283, 284, 285, 286, 287, 288, 289, 290, 290, 290, 290, 290, 290, 290, 290, 290, 290, 290, 290, 290, 290, 290, 290, 290, 290 ],
          "attributes": {
            "src": "designs/1892/top.sv:37.24-37.158"
          }
        },
        "$sub$designs/1892/top.sv:38$44_Y": {
          "hide_name": 1,
          "bits": [ 320, 321, 322, 323, 324, 325, 326, 327, 327, 327, 327 ],
          "attributes": {
            "src": "designs/1892/top.sv:38.84-38.140"
          }
        },
        "input_data": {
          "hide_name": 0,
          "bits": [ 2, 3, 4 ],
          "attributes": {
            "src": "designs/1892/top.sv:2.17-2.27"
          }
        },
        "output_data": {
          "hide_name": 0,
          "bits": [ 5, 6, 7, 8, 9, 10 ],
          "attributes": {
            "src": "designs/1892/top.sv:3.18-3.29"
          }
        },
        "temp_0": {
          "hide_name": 0,
          "bits": [ 2, 81, 82, "0", "0", "0" ],
          "attributes": {
            "src": "designs/1892/top.sv:6.17-6.23"
          }
        },
        "temp_1": {
          "hide_name": 0,
          "bits": [ 117, 118, 119, 207, 208, 209, "0", "0", "0", "0", "0", "0", "0", "0", "0", "0", "0", "0", "0", "0", "0", "0", "0", "0" ],
          "attributes": {
            "src": "designs/1892/top.sv:7.18-7.24"
          }
        },
        "temp_10": {
          "hide_name": 0,
          "bits": [ 206, 206, 206, 206, 206, 206, 206, 206, 206, 206, 206, 206, 206, 206, 206, 206, 206, 206, 206, 206, 206, 206, 206, 206 ],
          "attributes": {
            "src": "designs/1892/top.sv:16.18-16.25"
          }
        },
        "temp_11": {
          "hide_name": 0,
          "bits": [ 291, 292, 293, 294, 295, 296, 297, 298, 299, 300, 301, 302, 303, 304, 305, 306, 307, 308, 309, 310, 311, 312, 313, 314, 315, 316, 317, 318, 319 ],
          "attributes": {
            "src": "designs/1892/top.sv:17.18-17.25"
          }
        },
        "temp_12": {
          "hide_name": 0,
          "bits": [ 175, 176, 177, 383, 384, 385, 386, 387, 388, 389, 390, 391, 392, 393, 394, 395, 396, 397 ],
          "attributes": {
            "src": "designs/1892/top.sv:18.18-18.25",
            "unused_bits": "6 7 8 9 10 11 12 13 14 15 16 17"
          }
        },
        "temp_2": {
          "hide_name": 0,
          "bits": [ 248, 249, 250, 251, 252, 253, 254, 254, 254, 254, 254 ],
          "attributes": {
            "src": "designs/1892/top.sv:8.18-8.24"
          }
        },
        "temp_4": {
          "hide_name": 0,
          "bits": [ 109, "0", "0", "0", "0", "0", "0", "0", "0", "0", "0", "0", "0", "0", "0", "0", "0" ],
          "attributes": {
            "src": "designs/1892/top.sv:10.18-10.24"
          }
        },
        "temp_7": {
          "hide_name": 0,
          "bits": [ 114, 115, 116, 134, 135, 136, 137, 138, 139, 140, "0" ],
          "attributes": {
            "src": "designs/1892/top.sv:13.18-13.24"
          }
        },
        "temp_8": {
          "hide_name": 0,
          "bits": [ 128, 129, 130, 255, 256, 257, 258, 259, 260, 261, 262, 263, 264, 265, 266, 267, 268, 269, 270, 271, 272, 152, 153, 154, 155, 156, 157, 158 ],
          "attributes": {
            "src": "designs/1892/top.sv:14.18-14.24"
          }
        },
        "temp_9": {
          "hide_name": 0,
          "bits": [ 180, 181, 182, 183, 184, 185, 186, 187, 188, 189, 190, 191, 192, 193, 194, 195, 196, 197, 198, 199, 200, 201, 202, 203, 204, 205 ],
          "attributes": {
            "src": "designs/1892/top.sv:15.18-15.24"
          }
        }
      }
    }
  }
}
